Workbook
Name \0: #REF!
Name \0: #REF!
Name \0: #REF!
Name \0: #REF!
Name \00: #REF!
Name \00: #REF!
Name \00: #REF!
Name \00: #REF!
Name \44333: #REF!
Name \44333: #REF!
Name \44333: #REF!
Name \44333: #REF!
Name \A: #REF!
Name \A: #REF!
Name \A: #REF!
Name \A: #REF!
Name \A: #REF!
Name \A: #REF!
Name \A: #REF!
Name \add9a: #REF!
Name \add9a: #REF!
Name \add9a: #REF!
Name \add9a: #REF!
Name \add9a: #REF!
Name \add9a: #REF!
Name \add9a: #REF!
Name \B: #REF!
Name \B: #REF!
Name \B: #REF!
Name \B: #REF!
Name \B: #REF!
Name \B: #REF!
Name \B: #REF!
Name \C: #REF!
Name \C: #REF!
Name \C: #REF!
Name \C: #REF!
Name \C: #REF!
Name \C: #REF!
Name \C: #REF!
Name \D: #REF!
Name \D: #REF!
Name \D: #REF!
Name \D: #REF!
Name \D: #REF!
Name \D: #REF!
Name \D: #REF!
Name \E: #REF!
Name \E: #REF!
Name \E: #REF!
Name \E: #REF!
Name \E: #REF!
Name \E: #REF!
Name \E: #REF!
Name \H: #REF!
Name \H: #REF!
Name \H: #REF!
Name \H: #REF!
Name \H: #REF!
Name \H: #REF!

Sheet FEE RECON RAIHAN
A1: DCH - A9 & A10 | C1: MIRAGE INTERNAL | D1: Combined
A2: FOR EMAAR
A3: MIRAGE MULTI-DISCIPLINARY FEE PROPOSAL
A4: FEE RECONCILIATION
A5: R00
A6: ALL VALUES IN AED AND EXCLUDE TAX | E6: 0.1
C7: BUDGET | F7: FEES RECEIVED
A8: ITEM | B8: DISCIPLINE / TRADE | C8: CONSULTANT | D8: FEE | F8: A9 | G8: A10 | H8: A9 + A10 Fee | I8: Variance from Budgeted Fee
A9: A | B9: PRE-CONTRACT FEE (PM & DESIGN)
A10: 1.01 | B10: Design Project Management | C10: Mirage | D10: 500000 | E10: =D10/0.8 -> 625000 | F10: 638918 | G10: 638918 | H10: =F10+G10 -> 1277836 | I10: =D10-H10 -> -777836
A11: 1.01 | B11: Concept Architect | D11: Included | H11: =F11+G11 -> 0
A12: =A10+0.01 -> 1.02 | B12: Architecture - Tender Documents, Procurement and IFC | D12: 3000000 | E12: =D12/0.8 -> 3750000 | F12: 2032787 | G12: 2032787 | H12: =F12+G12 -> 4065574 | I12: =D12-H12 -> -1065574
A13: =A12+0.01 -> 1.03 | B13: Structural & Geotechnical Engineering | D13: 2200000 | E13: =D13/0.8 -> 2750000 | F13: 1346573 | G13: 1346573 | H13: =F13+G13 -> 2693146 | I13: =D13-H13 -> -493146
A14: =A13+0.01 -> 1.04 | B14: Landscaping, Swimming Pools & Water Features | D14: 600000 | E14: =D14/0.8 -> 750000 | F14: 693233 | G14: 693233 | H14: =F14+G14 -> 1386466 | I14: =D14-H14 -> -786466
A15: =A14+0.01 -> 1.05 | B15: MEPD Engineering | D15: 1300000 | E15: =D15/0.8 -> 1625000 | F15: 1048910 | G15: 1048910 | H15: =F15+G15 -> 2097820 | I15: =D15-H15 -> -797820
A16: =A15+0.01 -> 1.06 | B16: Quantity Surveying / Cost Management (excl.) | D16: 0 | H16: =F16+G16 -> 0 | I16: =D16-H16 -> 0
A17: =+A16+0.01 -> 1.07 | B17: Sub-Total Mirage | D17: =SUM(D10:D16) -> 7600000 | E17: =SUM(E10:E16) -> 9500000 | F17: =SUM(F10:F16) -> 5760421 | G17: =SUM(G10:G16) -> 5760421 | H17: =F17+G17 -> 11520842 | I17: =D17-H17 -> -3920842
A18: =+A17+0.01 -> 1.08 | B18: Architectural, ID and Structural Specification Writing Only | C18: Incl in Arch STR & ID fee | D18: Included | H18: =F18+G18 -> 0
A19: =+A18+0.01 -> 1.09 | B19: AOR | D19: Included | H19: =F19+G19 -> 0
A20: =+A19+0.01 -> 1.1 | B20: Civil Engineering | D20: Included within plot | H20: =F20+G20 -> 0
A21: =+A20+0.01 -> 1.11 | B21: Interior Design | C21: PH Design | D21: =750000*1.5 -> 1125000 | E21: =D21/0.9 -> 1250000 | F21: 763120 | G21: 763120 | H21: =F21+G21 -> 1526240 | I21: =D21-H21 -> -401240 | J21: PH Design
A22: =+A21+0.01 -> 1.12 | B22: Artwork | D22: Excluded | H22: =F22+G22 -> 0
A23: =+A22+0.01 -> 1.13 | B23: Telecom | C23: Emaar Technologies | D23: 140000 | E23: =D23/0.9 -> 155555.56 | F23: 72000 | G23: 72000 | H23: =F23+G23 -> 144000 | I23: =D23-H23 -> -4000 | J23: Emaar Technologies
A24: =+A23+0.01 -> 1.14 | B24: Acoustics | C24: Inhabit | D24: 60000 | E24: =D24/0.9 -> 66666.667 | F24: 58000 | G24: 58000 | H24: =F24+G24 -> 116000 | I24: =D24-H24 -> -56000 | J24: Inhabit
A25: =+A24+0.01 -> 1.15 | B25: Fire & Life Safety (excl CFD) | C25: Vortex | D25: 130000 | E25: =D25/0.9 -> 144444.44 | F25: 72500 | G25: 72500 | H25: =F25+G25 -> 145000 | I25: =D25-H25 -> -15000 | J25: Vortex
A26: =+A25+0.01 -> 1.16 | B26: Vertical Transport | D26: 125000 | E26: =D26/0.9 -> 138888.89 | F26: 75000 | G26: 75000 | H26: =F26+G26 -> 150000 | I26: =D26-H26 -> -25000
A27: =+A26+0.01 -> 1.17 | B27: Sustainability (Minimum DM Requirements) | C27: Platinum | D27: 60000 | E27: =D27/0.9 -> 66666.667 | F27: 40500 | G27: 40500 | H27: =F27+G27 -> 81000 | I27: =D27-H27 -> -21000 | J27: Platinum
A28: =+A27+0.01 -> 1.18 | B28: Wind Engineering | C28: RWDI/CPP | D28: 300000 | E28: =D28/0.9 -> 333333.33 | F28: 156250 | G28: 156250 | H28: =F28+G28 -> 312500 | I28: =D28-H28 -> -12500 | J28: RWDI
A29: =+A28+0.01 -> 1.19 | B29: Façade & BMU | C29: Thomas Bell-Wright | D29: 390000 | E29: =D29/0.9 -> 433333.33 | F29: 390000 | G29: 390000 | H29: =F29+G29 -> 780000 | I29: =D29-H29 -> -390000 | J29: Thomas Bell-Wright
A30: =+A29+0.01 -> 1.2 | B30: Specialist Lighting | C30: Studio Lumen | D30: 130000 | E30: =D30/0.9 -> 144444.44 | F30: 75000 | G30: 75000 | H30: =F30+G30 -> 150000 | I30: =D30-H30 -> -20000
A31: =+A30+0.01 -> 1.21 | B31: Signage & Wayfinding | D31: 0 | H31: =F31+G31 -> 0 | I31: =D31-H31 -> 0
A32: =+A31+0.01 -> 1.22 | B32: Waste Management | C32: MCTS | D32: 50000 | E32: =D32/0.9 -> 55555.556 | F32: 39000 | G32: 39000 | H32: =F32+G32 -> 78000 | I32: =D32-H32 -> -28000 | J32: MCTS
A33: =+A32+0.01 -> 1.23 | B33: Spa Consultant - Spa Enabler | D33: Excluded | H33: =F33+G33 -> 0
A34: =+A33+0.01 -> 1.24 | B34: Traffic Engineering (TIS - Level 1) | C34: Al Turath | D34: 90000 | E34: =D34/0.9 -> 100000 | F34: 50000 | G34: 50000 | H34: =F34+G34 -> 100000 | I34: =D34-H34 -> -10000
A35: =+A34+0.01 -> 1.25 | B35: Topographical Survey | D35: Excluded | H35: =F35+G35 -> 0
A36: =+A35+0.01 -> 1.26 | B36: F&B, Kitchen | D36: Excluded | H36: =F36+G36 -> 0
A37: =+A36+0.01 -> 1.27 | B37: F&B Concept Enabler | D37: Excluded | H37: =F37+G37 -> 0
A38: =+A37+0.01 -> 1.28 | B38: Laundry | D38: Excluded | H38: =F38+G38 -> 0
A39: =+A38+0.01 -> 1.29 | B39: Gym Consultant | D39: Excluded | H39: =F39+G39 -> 0
A40: =+A39+0.01 -> 1.3 | B40: Procurement Agent | C40: Exclude this | D40: Excluded | H40: =F40+G40 -> 0
A41: =+A40+0.01 -> 1.31 | B41: EIA (Minimum Local Requirements) | D41: Excluded | H41: =F41+G41 -> 0
A42: =+A41+0.01 -> 1.32 | B42: 3rd Party Structural & Geotechnical Review | C42: Salama | D42: 500000 | E42: =D42/0.9 -> 555555.56 | F42: 355000 | G42: 355000 | H42: =F42+G42 -> 710000 | I42: =D42-H42 -> -210000
A43: =+A42+0.01 -> 1.33 | B43: Security | C43: CKR | D43: 140000 | E43: =D43/0.9 -> 155555.56 | F43: 82500 | G43: 82500 | H43: =F43+G43 -> 165000 | I43: =D43-H43 -> -25000
A44: =+A43+0.01 -> 1.34 | B44: 3rd Party MEPD Review | D44: Excluded | H44: =F44+G44 -> 0
A45: =+A44+0.01 -> 1.35 | B45: 3rd Party Fire, Life & Safety Review | D45: Excluded | H45: =F45+G45 -> 0
A46: =+A45+0.01 -> 1.36 | B46: 3rd Party Cost Review | D46: Excluded | H46: =F46+G46 -> 0
A47: =+A46+0.01 -> 1.37 | B47: Aeronautical Survey | C47: Nortech | D47: 40000 | E47: =D47/0.9 -> 44444.444 | F47: 16040 | G47: 16040 | H47: =F47+G47 -> 32080 | I47: =D47-H47 -> 7920 | J47: Nortech
A48: =+A47+0.01 -> 1.38 | B48: Physical Scale Model | D48: Excluded | H48: =F48+G48 -> 0
A49: A.1 | B49: Subtotal - Sub-Consultants | D49: =SUM(D18:D48) -> 3280000 | E49: =SUM(E18:E48) -> 3644444.4 | F49: =SUM(F18:F48) -> 2244910 | G49: =SUM(G18:G48) -> 2244910 | H49: =SUM(H18:H48) -> 4489820 | I49: =D49-H49 -> -1209820
A51: A.2 | B51: Expenses (no travel considered) | E51: =E49+E17 -> 13144444 | F51: =E51/2 -> 6572222.2
A53: A.3 | B53: Sub Total: Pre-Contract Costs | D53: =D51+D49+D17 -> 10880000
A54: A.4 | B54: Risk / Contingency | C54: 0.05 | D54: =C54*(D53/(1-SUM($C$54:$C$56))) -> 640000
A55: A.5 | B55: Negotiation | D55: =C55*(D53/(1-SUM($C$54:$C$56))) -> 0
A56: A.6 | B56: Markup / Margin | C56: 0.1 | D56: =C56*(D53/(1-SUM($C$54:$C$56))) -> 1280000
A57: A | B57: TOTAL PRE-CONTRACT FEE (DM, PM & DESIGN) | D57: =SUM(D53:D56) -> 12800000 | E57: =D57/2 -> 6400000
A59: B | B59: POST-CONTRACT FEE (PMC & TECHNICAL) | D59: FEE
A60: 2.01 | B60: PMC
A61: =A60+0.01 -> 2.02 | B61: QS / Cost Management (Excluded) | D61: 0
A62: =A61+0.01 -> 2.03 | B62: Technical Site Supervision | D62: =#REF! -> #REF!
A63: =A62+0.01 -> 2.04 | B63: Technical Site Supervision Sub-Consultants | D63: =#REF! -> #REF!
A64: =A63+0.01 -> 2.05 | B64: DLP Allowance (12 Months) | D64: =#REF! -> #REF!
A65: =A64+0.01 -> 2.06 | B65: Expenses (no travel considered)
A66: B.1 | B66: Sub-total: Post-Contract Services | D66: =SUM(D60:D65) -> #REF!
A67: B.2 | B67: Risk / Contingency | D67: =C67*(D66/(1-SUM($C$67:$C$69))) -> #REF!
A68: B.3 | B68: Negotiation | D68: =C68*(D66/(1-SUM($C$67:$C$69))) -> #REF!
A69: B.4 | B69: Markup / Margin | D69: =C69*(D66/(1-SUM($C$67:$C$69))) -> #REF!
A70: B | B70: TOTAL POST-CONTRACT FEE (PMC & TECHNICAL) | D70: =SUM(D66:D69) -> #REF!
A72: C | B72: TOTAL FEE PROPOSAL | D72: =D57+D70 -> #REF!
A73: C.1 | B73: Pre-Contract Fee | D73: =D57 -> 12800000
A74: C.2 | B74: Post-Contract Fee | D74: =D70 -> #REF!
A76: D | B76: FEE AVAILABLE | D76: 16025230
A77: D.1 | B77: Variance | D77: =+D72-D76 -> #REF!
C79: Margin Check | D79: =D69+D56 -> #REF!
C80: Risk / Contingency Check | D80: =D54+D67 -> #REF!
C81: Negotiation Check | D81: =+D68+D55 -> #REF!
C82: Total | D82: =SUM(D79:D81) -> #REF!
A84: D | B84: TARGET HARD COST (AED) (UNFURNISHED, UNSERVICED) INCLUDING WHITE GOODS TO APTS & FFE / OSE TO PUBLIC AREAS | C84: =#REF! -> #REF! | D84: =#REF! -> #REF!
B87: QS Fee
B88: BUA up to 32,5000 ft2 | C88: 0.0065
B89: Fee | C89: =ROUND(C84*C88,0) -> #REF! | D89: including Margin
B90: Omit Margin & Contingencies | C90: =ROUND(C89*0.8,0) -> #REF!
B91: Pre | C91: =ROUND($C$90*D91,0) -> #REF! | D91: 0.22
B92: Post | C92: =ROUND($C$90*D92,0) -> #REF! | D92: 0.78

Sheet A9 Design + Subs fee 
H2: 0.25 | I2: 0.3 | J2: 0.35 | K2: 0.05 | L2: 0.05
B3: DCH. A9
B4: DESIGN CONSULTANCY SERVICES
B7: FEE BREAKDOWN
B9: Professional Discipline | C9: Sub-Consultant
D10: Signed NDA Received | E10: FROM Subs | F10: Fees 31.05.24 | G10: BUDGET | H10: Concept Design | I10: Stage 2 Schematic Design | J10: Stage 3 Detail Design | K10: Stage 4 Tender Docs, Tender Services & Evaluation | L10: Stage 5 IFC & Contract Documentation | M10: Total Design | N10: Supervision | O10: Total A
B12: =B4 -> DESIGN CONSULTANCY SERVICES | Q12: 3.6725
A13: 1 | M13: =SUM(H13:L13) -> 0 | O13: =M13+N13 -> 0 | Q13: USD
A14: =A13+1 -> 2 | B14: Architecture (PCD to DD) | C14: DPA (Upto SD) | E14: 3305250 | F14: 6133075 | G14: 6200000 | H14: =G14*$H$2 -> 1550000 | I14: =G14*$I$2 -> 1860000 | J14: =G14*$J$2 -> 2170000 | K14: =G14*$K$2 -> 310000 | L14: =G14*$L$2 -> 310000 | M14: =SUM(H14:L14) -> 6200000 | O14: =M14+N14 -> 6200000 | P14: DPA | Q14: =E14/$Q$12 -> 900000 | R14: check AOR
C15: DD | E15: 2276950 | Q15: =E15/$Q$12 -> 620000
C16: TD/IFC Review | E16: 550875 | Q16: =E16/$Q$12 -> 150000
E17: =SUM(E14:E16) -> 6133075 | Q17: =E17/$Q$12 -> 1670000
B18: Architecture 02 (PCD ONLY) | C18: OMA (Upto SD) | E18: 3344690 | F18: =Q18*Q12 -> 565565 | G18: 565565 | P18: OMA (PCD) | Q18: =77000*2 -> 154000 | R18: =112500*2 -> 225000 | S18: =R18*Q12 -> 826312.5
C19: DD | E19: 3915565.5 | G19: `
C20: TD & IFC Rev / month | E20: 187425
E21: =SUM(E18:E20) -> 7447680.5 | Q21: 385000
B22: Strategy, Brand Identity | C22: Chandelier | E22: =Q21*Q12 -> 1413912.5 | F22: =E22 -> 1413912.5 | G22: 1500000
Q23: 42750
B24: Ideation Consultancy (ID Briefing) | C24: ERA | E24: =Q23*Q12 -> 156999.38 | G24: 180000
A26: =A14+1 -> 3 | B26: AOR | C26: Chawla Architects | F26: 350000 | G26: 350000 | H26: =G26*$H$2 -> 87500 | I26: =G26*$I$2 -> 105000 | J26: =G26*$J$2 -> 122500 | K26: =G26*$K$2 -> 17500 | L26: =G26*$L$2 -> 17500 | M26: =SUM(H26:L26) -> 350000 | O26: =M26+N26 -> 350000
C27: Dubai Consultants
A29: =A26+1 -> 4 | B29: Geotechnical Design | C29: RBG | E29: 275000 | F29: 275000 | G29: 275000 | H29: =G29*$H$2 -> 68750 | I29: =G29*$I$2 -> 82500 | J29: =G29*$J$2 -> 96250 | K29: =G29*$K$2 -> 13750 | L29: =G29*$L$2 -> 13750 | M29: =SUM(H29:L29) -> 275000 | O29: =M29+N29 -> 275000
C30: Coffey | E30: 226275
A32: =A29+1 -> 5 | B32: MEP | C32: CKR | E32: 1330000 | F32: 1300000 | G32: 1500000 | H32: =G32*$H$2 -> 375000 | I32: =G32*$I$2 -> 450000 | J32: =G32*$J$2 -> 525000 | K32: =G32*$K$2 -> 75000 | L32: =G32*$L$2 -> 75000 | M32: =SUM(H32:L32) -> 1500000 | O32: =M32+N32 -> 1500000
C33: Consistent Engineering Consultants | M33: =SUM(H33:L33) -> 0 | O33: =M33+N33 -> 0
C34: WME | E34: 1450000 | M34: =SUM(H34:L34) -> 0 | O34: =M34+N34 -> 0
A36: =A32+1 -> 6 | B36: Interior Design | C36: PH Design | D36: Yes | E36: 763120 | H36: =G36*$H$2 -> 0 | I36: =G36*$I$2 -> 0 | J36: =G36*$J$2 -> 0 | K36: =G36*$K$2 -> 0 | L36: =G36*$L$2 -> 0 | M36: =SUM(H36:L36) -> 0 | O36: =M36+N36 -> 0 | R36: =E36/3.67 -> 207934.6 | S36: 300000
C37: LW Design | D37: Yes | E37: Declined | M37: =SUM(H37:L37) -> 0 | R37: =E37/3.67 -> #VALUE! | S37: =S36/25 -> 12000 | T37: =S37/3.67 -> 3269.7548
C38: DSGN | D38: Yes | E38: 1060000 | R38: =E38/3.67 -> 288828.34
A40: =A36+1 -> 7 | B40: Specialist Lighting | C40: Lightvision | H40: =G40*$H$2 -> 0 | I40: =G40*$I$2 -> 0 | J40: =G40*$J$2 -> 0 | K40: =G40*$K$2 -> 0 | L40: =G40*$L$2 -> 0 | M40: =SUM(H40:L40) -> 0 | O40: =M40+N40 -> 0
C41: CD+M | D41: Yes | E41: 437500 | M41: =SUM(H41:L41) -> 0
C42: Nulty Lighting | D42: Yes | E42: 386000 | M42: =SUM(H42:L42) -> 0
C43: Studio Lumen | D43: Yes | E43: 75000 | M43: =SUM(H43:L43) -> 0
C44: LDPi | D44: Yes | E44: 500000
A46: =A40+1 -> 8 | B46: Façade and BMU | C46: Thomas Bell-Wright International Consultants | D46: Yes | E46: 390000 | H46: =G46*$H$2 -> 0 | I46: =G46*$I$2 -> 0 | J46: =G46*$J$2 -> 0 | K46: =G46*$K$2 -> 0 | L46: =G46*$L$2 -> 0 | M46: =SUM(H46:L46) -> 0 | O46: =M46+N46 -> 0
C47: Meinhardt | D47: Yes | E47: 576604
C48: AESG | D48: Yes | E48: 423000
C49: Ramboll | D49: Yes
C50: Warner Sobek | D50: Yes | M50: =SUM(H50:L50) -> 0 | O50: =M50+N50 -> 0
A52: =A46+1 -> 9 | B52: Signage & Wayfinding Consultant | C52: Brimaxx | D52: Yes | E52: 162500 | H52: =G52*$H$2 -> 0 | I52: =G52*$I$2 -> 0 | J52: =G52*$J$2 -> 0 | K52: =G52*$K$2 -> 0 | L52: =G52*$L$2 -> 0 | M52: =SUM(H52:L52) -> 0 | O52: =M52+N52 -> 0
C53: Brimaxx (A9+A10 Combined Offer) | D53: Yes | E53: 138750
C54: Endpoint | D54: Yes | E54: 187500 | M54: =SUM(H54:L54) -> 0 | O54: =M54+N54 -> 0
C55: Trade Inclusive DMCC | D55: Yes | E55: 38250
A57: =A52+1 -> 10 | B57: Wind Tunnel Testing | C57: CPP | D57: Yes | H57: =G57*$H$2 -> 0 | I57: =G57*$I$2 -> 0 | J57: =G57*$J$2 -> 0 | K57: =G57*$K$2 -> 0 | L57: =G57*$L$2 -> 0 | M57: =SUM(H57:L57) -> 0 | O57: =M57+N57 -> 0 | W57: 294
C58: RWDI | D58: Yes | E58: 156250
A60: =A57+1 -> 11 | B60: Security | C60: CKR | D60: Yes | E60: 82500 | G60: 0 | H60: =G60*$H$2 -> 0 | I60: =G60*$I$2 -> 0 | J60: =G60*$J$2 -> 0 | K60: =G60*$K$2 -> 0 | L60: =G60*$L$2 -> 0 | M60: =SUM(H60:L60) -> 0 | O60: =M60+N60 -> 0 | W60: 29
C61: Jensen Hughes | D61: Yes | E61: 94650 | M61: =SUM(H61:L61) -> 0 | O61: =M61+N61 -> 0 | W61: =SUM(W57:W60) -> 323
A63: =A60+1 -> 12 | B63: Telecom (AV/ICT) | C63: Emaar Tech | D63: Yes | E63: 72000 | H63: =G63*$H$2 -> 0 | I63: =G63*$I$2 -> 0 | J63: =G63*$J$2 -> 0 | K63: =G63*$K$2 -> 0 | L63: =G63*$L$2 -> 0 | M63: =SUM(H63:L63) -> 0 | O63: =M63+N63 -> 0
C64: NV5 | D64: Yes | E64: 267710
M65: =SUM(H65:L65) -> 0 | O65: =M65+N65 -> 0
A66: =A63+1 -> 13 | B66: Pools & Water Specialist | C66: Barr + Wray | H66: =G66*$H$2 -> 0 | I66: =G66*$I$2 -> 0 | J66: =G66*$J$2 -> 0 | K66: =G66*$K$2 -> 0 | L66: =G66*$L$2 -> 0 | M66: =SUM(H66:L66) -> 0 | O66: =M66+N66 -> 0
C67: Starpool | M67: =SUM(H67:L67) -> 0 | O67: =M67+N67 -> 0
C68: The Wellness | D68: Yes | E68: 75000 | M68: =SUM(H68:L68) -> 0 | O68: =M68+N68 -> 0
C69: EME | D69: Yes | E69: 99000
A71: =A66+1 -> 14 | B71: Fire Life Study | C71: Vortex | D71: Yes | E71: 72500 | H71: =G71*$H$2 -> 0 | I71: =G71*$I$2 -> 0 | J71: =G71*$J$2 -> 0 | K71: =G71*$K$2 -> 0 | L71: =G71*$L$2 -> 0 | M71: =SUM(H71:L71) -> 0 | O71: =M71+N71 -> 0
C72: Design Confidence | D72: Yes | E72: 150000
C73: Jensen Hughes | D73: Yes | E73: 175000
C74: AESG | D74: Yes | E74: 240000
X75: 30000
A76: =A71+1 -> 15 | B76: Vertical Transportation | C76: Barker Mohandas | D76: Yes | H76: =G76*$H$2 -> 0 | I76: =G76*$I$2 -> 0 | J76: =G76*$J$2 -> 0 | K76: =G76*$K$2 -> 0 | L76: =G76*$L$2 -> 0 | M76: =SUM(H76:L76) -> 0 | O76: =M76+N76 -> 0 | X76: 25000
C77: RBA Vertical Transportation Consultants | D77: Yes | E77: 64000 | M77: =SUM(H77:L77) -> 0 | O77: =M77+N77 -> 0 | X77: 25000
A79: =A76+1 -> 16 | B79: Traffic Impact Study | C79: Zutari | E79: Declined | H79: =G79*$H$2 -> 0 | I79: =G79*$I$2 -> 0 | J79: =G79*$J$2 -> 0 | K79: =G79*$K$2 -> 0 | L79: =G79*$L$2 -> 0 | M79: =SUM(H79:L79) -> 0 | O79: =M79+N79 -> 0 | X79: 12500
C80: Al Turath | D80: Yes | E80: 50000 | X80: 5000
C81: Infracad
C82: CDM Smith | D82: Yes | E82: Declined
C83: Transpo
A85: =A79+1 -> 17 | B85: Acoustics | C85: Inhabit | D85: Yes | E85: 58000 | H85: =G85*$H$2 -> 0 | I85: =G85*$I$2 -> 0 | J85: =G85*$J$2 -> 0 | K85: =G85*$K$2 -> 0 | L85: =G85*$L$2 -> 0 | M85: =SUM(H85:L85) -> 0 | O85: =M85+N85 -> 0 | X85: =SUM(X75:X80) -> 97500
C86: Ramboll | D86: Yes
C87: DARL | D87: Yes | E87: 78000 + 15500
C88: AESG | D88: Yes | E88: 112000
A90: =A85+1 -> 18 | B90: 3rd Party Structural Peer Review | C90: Qualiconsult | H90: =G90*$H$2 -> 0 | I90: =G90*$I$2 -> 0 | J90: =G90*$J$2 -> 0 | K90: =G90*$K$2 -> 0 | L90: =G90*$L$2 -> 0 | M90: =SUM(H90:L90) -> 0 | O90: =M90+N90 -> 0
C91: SSE | D91: Yes
O92: =M92+N92 -> 0
A93: =A90+1 -> 19 | B93: 3rd Party Geotechnical Peer Review | C93: Qualiconsult | H93: =G93*$H$2 -> 0 | I93: =G93*$I$2 -> 0 | J93: =G93*$J$2 -> 0 | K93: =G93*$K$2 -> 0 | L93: =G93*$L$2 -> 0 | M93: =SUM(H93:L93) -> 0 | O93: =M93+N93 -> 0
C94: SSE | D94: Yes
O95: =M95+N95 -> 0
A96: =A93+1 -> 20 | B96: Aeronautical | C96: Nortech | D96: Yes | E96: 16040 | H96: =G96*$H$2 -> 0 | I96: =G96*$I$2 -> 0 | J96: =G96*$J$2 -> 0 | K96: =G96*$K$2 -> 0 | L96: =G96*$L$2 -> 0 | M96: =SUM(H96:L96) -> 0 | O96: =M96+N96 -> 0
A98: =A96+1 -> 21 | B98: DMGBC / Al Sa’fat Green Building Facilitation | C98: PSDI | D98: Yes | E98: 40500 | H98: =G98*$H$2 -> 0 | I98: =G98*$I$2 -> 0 | J98: =G98*$J$2 -> 0 | K98: =G98*$K$2 -> 0 | L98: =G98*$L$2 -> 0 | M98: =SUM(H98:L98) -> 0 | O98: =M98+N98 -> 0
M99: =SUM(H99:L99) -> 0
B100: Waste Management | C100: CDS | D100: Yes | E100: 39000
C101: MCTS | D101: Yes | E101: 118200
A103: 22 | B103: Building Services | C103: NV5 | D103: Yes | E103: 2395880
C104: GCE | D104: Yes
B106: Soil Investigation | C106: By Client | H106: =G106*$H$2 -> 0 | I106: =G106*$I$2 -> 0 | J106: =G106*$J$2 -> 0 | K106: =G106*$K$2 -> 0 | L106: =G106*$L$2 -> 0 | M106: =SUM(H106:L106) -> 0 | O106: =M106+N106 -> 0
A107: =A103+1 -> 23 | B107: Topographical Survey | C107: By Client | H107: =G107*$H$2 -> 0 | I107: =G107*$I$2 -> 0 | J107: =G107*$J$2 -> 0 | K107: =G107*$K$2 -> 0 | L107: =G107*$L$2 -> 0 | M107: =SUM(H107:L107) -> 0 | O107: =M107+N107 -> 0
B108: External Renderings | C108: By Client
B109: Environmental Impact Study | C109: By Client | H109: =G109*$H$2 -> 0 | I109: =G109*$I$2 -> 0 | J109: =G109*$J$2 -> 0 | K109: =G109*$K$2 -> 0 | L109: =G109*$L$2 -> 0
A110: =A107+1 -> 24 | B110: Misc. Budget - Subs | H110: =G110*$H$2 -> 0 | I110: =G110*$I$2 -> 0 | J110: =G110*$J$2 -> 0 | K110: =G110*$K$2 -> 0 | L110: =G110*$L$2 -> 0 | M110: =SUM(H110:L110) -> 0 | O110: =M110+N110 -> 0
A111: =A110+1 -> 25 | B111: TOTAL SUB-CONSULTANT FEE (INCL CONT) | F111: =SUM(F13:F110) -> 10037552 | G111: =SUM(G13:G110) -> 10570565 | H111: =SUM(H13:H110) -> 2081250 | I111: =SUM(I13:I110) -> 2497500 | J111: =SUM(J13:J110) -> 2913750 | K111: =SUM(K13:K110) -> 416250 | L111: =SUM(L13:L110) -> 416250 | M111: =SUM(M13:M110) -> 8325000 | ... O111: =SUM(O13:O110) -> 8325000
A112: =A111+1 -> 26 | B112: Architecture & Project Manager (Mirage Design) | C112: Mirage | F112: 2000000 | G112: 2000000 | H112: =G112*$H$2 -> 500000 | I112: =G112*$I$2 -> 600000 | J112: =G112*$J$2 -> 700000 | K112: =G112*$K$2 -> 100000 | L112: =G112*$L$2 -> 100000 | M112: =SUM(H112:L112) -> 2000000 | O112: =M112+N112 -> 2000000
A113: =A112+1 -> 27 | B113: Structures | C113: Mirage | F113: 2500000 | G113: 2500000 | H113: =G113*$H$2 -> 625000 | I113: =G113*$I$2 -> 750000 | J113: =G113*$J$2 -> 875000 | K113: =G113*$K$2 -> 125000 | L113: =G113*$L$2 -> 125000 | M113: =SUM(H113:L113) -> 2500000 | O113: =M113+N113 -> 2500000
A114: =A113+1 -> 28 | B114: Landscape | C114: Mirage
A115: =A114+1 -> 29 | B115: Design support during Construction - Mirage | C115: Mirage | H115: =G115*$H$2 -> 0 | I115: =G115*$I$2 -> 0 | J115: =G115*$J$2 -> 0 | K115: =G115*$K$2 -> 0 | L115: =G115*$L$2 -> 0 | M115: =SUM(H115:L115) -> 0 | O115: =M115+N115 -> 0
A116: =A115+1 -> 30 | B116: Direct Costs (Aconex, PI Insurance, etc) Other Misc. Expenses | C116: Mirage | F116: 100000 | G116: 100000 | H116: =G116*$H$2 -> 25000 | I116: =G116*$I$2 -> 30000 | J116: =G116*$J$2 -> 35000 | K116: =G116*$K$2 -> 5000 | L116: =G116*$L$2 -> 5000 | M116: =SUM(H116:L116) -> 100000 | O116: =M116+N116 -> 100000
O117: =M117+N117 -> 0
B118: TOTAL FEE FOR COMPONENT | F118: =SUM(F111:F117) -> 14637552 | G118: =SUM(G111:G117) -> 15170565 | H118: =SUM(H111:H117) -> 3231250 | I118: =SUM(I111:I117) -> 3877500 | J118: =SUM(J111:J117) -> 4523750 | K118: =SUM(K111:K117) -> 646250 | L118: =SUM(L111:L117) -> 646250 | M118: =SUM(M111:M117) -> 12925000 | ... O118: =SUM(O111:O117) -> 12925000
B119: Design Contingency @15% | F119: =F118*15% -> 2195632.9 | G119: =G118*15% -> 2275584.8 | H119: =G119*$H$2 -> 568896.19 | I119: =G119*$I$2 -> 682675.42 | J119: =G119*$J$2 -> 796454.66 | K119: =G119*$K$2 -> 113779.24 | L119: =G119*$L$2 -> 113779.24 | M119: =SUM(H119:L119) -> 2275584.7 | O119: =M119+N119 -> 2275584.7
B120: TOTAL MARGIN @ 10% | F120: =P122 -> 0 | G120: =R122 -> 1938461.1 | H120: =G120*$H$2 -> 484615.27 | I120: =G120*$I$2 -> 581538.32 | J120: =G120*$J$2 -> 678461.38 | K120: =G120*$K$2 -> 96923.054 | L120: =G120*$L$2 -> 96923.054 | M120: =SUM(H120:L120) -> 1938461.1 | O120: =M120+N120 -> 1938461.1 | R120: =G118+G119 -> 17446150
B121: TOTAL DESIGN | F121: =SUM(F118:F120) -> 16833185 | G121: =SUM(G118:G120) -> 19384611 | H121: =SUM(H118:H120) -> 4284761.5 | I121: =SUM(I118:I120) -> 5141713.8 | J121: =SUM(J118:J120) -> 5998666 | K121: =SUM(K118:K120) -> 856952.29 | L121: =SUM(L118:L120) -> 856952.29 | M121: =SUM(M118:M120) -> 17139046 | ... O121: =SUM(O118:O120) -> 17139046 | R121: =R120/0.9 -> 19384611
H122: 0.25 | I122: 0.3 | J122: 0.35 | K122: 0.05 | L122: 0.05 | R122: =R121*10% -> 1938461.1
...

Sheet A10 Design + Subs fee
H2: 0.25 | I2: 0.3 | J2: 0.35 | K2: 0.05 | L2: 0.05
B3: DCH. A10
B4: DESIGN CONSULTANCY SERVICES
B7: FEE BREAKDOWN
B9: Professional Discipline | C9: Sub-Consultant
D10: Signed NDA Received | E10: FROM Subs | F10: Fees 31.05.24 | G10: BUDGET | H10: Concept Design | I10: Stage 2 Schematic Design | J10: Stage 3 Detail Design | K10: Stage 4 Tender Docs, Tender Services & Evaluation | L10: Stage 5 IFC & Contract Documentation | M10: Total Design | N10: Supervision | O10: Total A
B12: =B4 -> DESIGN CONSULTANCY SERVICES | Q12: 3.6725
A13: 1 | M13: =SUM(H13:L13) -> 0 | O13: =M13+N13 -> 0 | Q13: USD
A14: =A13+1 -> 2 | B14: Architecture (PCD to DD) | C14: DPA (Upto SD) | E14: 3305250 | F14: 6133075 | G14: 6200000 | H14: =G14*$H$2 -> 1550000 | I14: =G14*$I$2 -> 1860000 | J14: =G14*$J$2 -> 2170000 | K14: =G14*$K$2 -> 310000 | L14: =G14*$L$2 -> 310000 | M14: =SUM(H14:L14) -> 6200000 | O14: =M14+N14 -> 6200000 | P14: DPA | Q14: =E14/$Q$12 -> 900000 | R14: check AOR
C15: DD | E15: 2276950 | Q15: =E15/$Q$12 -> 620000
C16: TD/IFC Review | E16: 550875 | Q16: =E16/$Q$12 -> 150000
E17: =SUM(E14:E16) -> 6133075 | Q17: =E17/$Q$12 -> 1670000
B18: Architecture 02 (PCD ONLY) | C18: OMA (Upto SD) | E18: 3344690 | F18: =Q18*Q12 -> 565565 | G18: 565565 | P18: OMA (PCD) | Q18: =77000*2 -> 154000 | R18: =112500*2 -> 225000 | S18: =R18*Q12 -> 826312.5
C19: DD | E19: 3915565.5 | G19: `
C20: TD & IFC Rev / month | E20: 187425
E21: =SUM(E18:E20) -> 7447680.5 | Q21: 385000
B22: Strategy, Brand Identity | C22: Chandelier | E22: =Q21*Q12 -> 1413912.5 | F22: =E22 -> 1413912.5 | G22: 1500000
Q23: 42750
B24: Ideation Consultancy (ID Briefing) | C24: ERA | E24: =Q23*Q12 -> 156999.38 | G24: 180000
A26: =A14+1 -> 3 | B26: AOR | C26: Chawla Architects | F26: 350000 | G26: 350000 | H26: =G26*$H$2 -> 87500 | I26: =G26*$I$2 -> 105000 | J26: =G26*$J$2 -> 122500 | K26: =G26*$K$2 -> 17500 | L26: =G26*$L$2 -> 17500 | M26: =SUM(H26:L26) -> 350000 | O26: =M26+N26 -> 350000
C27: Dubai Consultants
A29: =A26+1 -> 4 | B29: Geotechnical Design | C29: RBG | E29: 275000 | F29: 275000 | G29: 275000 | H29: =G29*$H$2 -> 68750 | I29: =G29*$I$2 -> 82500 | J29: =G29*$J$2 -> 96250 | K29: =G29*$K$2 -> 13750 | L29: =G29*$L$2 -> 13750 | M29: =SUM(H29:L29) -> 275000 | O29: =M29+N29 -> 275000
C30: Coffey | E30: 226275
A32: =A29+1 -> 5 | B32: MEP | C32: CKR | E32: 1330000 | F32: 1300000 | G32: 1500000 | H32: =G32*$H$2 -> 375000 | I32: =G32*$I$2 -> 450000 | J32: =G32*$J$2 -> 525000 | K32: =G32*$K$2 -> 75000 | L32: =G32*$L$2 -> 75000 | M32: =SUM(H32:L32) -> 1500000 | O32: =M32+N32 -> 1500000
C33: Consistent Engineering Consultants | M33: =SUM(H33:L33) -> 0 | O33: =M33+N33 -> 0
C34: WME | E34: 1450000 | M34: =SUM(H34:L34) -> 0 | O34: =M34+N34 -> 0
A36: =A32+1 -> 6 | B36: Interior Design | C36: PH Design | D36: Yes | E36: 763120 | H36: =G36*$H$2 -> 0 | I36: =G36*$I$2 -> 0 | J36: =G36*$J$2 -> 0 | K36: =G36*$K$2 -> 0 | L36: =G36*$L$2 -> 0 | M36: =SUM(H36:L36) -> 0 | O36: =M36+N36 -> 0 | R36: =E36/3.67 -> 207934.6 | S36: 300000
C37: LW Design | D37: Yes | E37: Declined | M37: =SUM(H37:L37) -> 0 | R37: =E37/3.67 -> #VALUE! | S37: =S36/25 -> 12000 | T37: =S37/3.67 -> 3269.7548
C38: DSGN | D38: Yes | E38: 1060000 | R38: =E38/3.67 -> 288828.34
A40: =A36+1 -> 7 | B40: Specialist Lighting | C40: Lightvision | H40: =G40*$H$2 -> 0 | I40: =G40*$I$2 -> 0 | J40: =G40*$J$2 -> 0 | K40: =G40*$K$2 -> 0 | L40: =G40*$L$2 -> 0 | M40: =SUM(H40:L40) -> 0 | O40: =M40+N40 -> 0
C41: CD+M | D41: Yes | M41: =SUM(H41:L41) -> 0
C42: Nulty Lighting | D42: Yes | E42: 386000 | M42: =SUM(H42:L42) -> 0
C43: Studio Lumen | D43: Yes | E43: 75000 | M43: =SUM(H43:L43) -> 0
C44: LDPi | D44: Yes | E44: 500000
A46: =A40+1 -> 8 | B46: Façade and BMU | C46: Thomas Bell-Wright International Consultants | D46: Yes | E46: 390000 | H46: =G46*$H$2 -> 0 | I46: =G46*$I$2 -> 0 | J46: =G46*$J$2 -> 0 | K46: =G46*$K$2 -> 0 | L46: =G46*$L$2 -> 0 | M46: =SUM(H46:L46) -> 0 | O46: =M46+N46 -> 0
C47: Meinhardt | D47: Yes
C48: AESG | D48: Yes | E48: 423000
C49: Ramboll
C50: Warner Sobek | D50: Yes | M50: =SUM(H50:L50) -> 0 | O50: =M50+N50 -> 0
A52: =A46+1 -> 9 | B52: Signage & Wayfinding Consultant | C52: Brimaxx | D52: Yes | E52: 162500 | H52: =G52*$H$2 -> 0 | I52: =G52*$I$2 -> 0 | J52: =G52*$J$2 -> 0 | K52: =G52*$K$2 -> 0 | L52: =G52*$L$2 -> 0 | M52: =SUM(H52:L52) -> 0 | O52: =M52+N52 -> 0
C53: Brimaxx (A9+A10 Combined Offer) | D53: Yes | E53: 138750
C54: Endpoint | D54: Yes | E54: 187500 | M54: =SUM(H54:L54) -> 0 | O54: =M54+N54 -> 0
C55: Trade Inclusive DMCC | D55: Yes | E55: 38250
A57: =A52+1 -> 10 | B57: Wind Tunnel Testing | C57: CPP | D57: Yes | H57: =G57*$H$2 -> 0 | I57: =G57*$I$2 -> 0 | J57: =G57*$J$2 -> 0 | K57: =G57*$K$2 -> 0 | L57: =G57*$L$2 -> 0 | M57: =SUM(H57:L57) -> 0 | O57: =M57+N57 -> 0 | W57: 294
C58: RWDI | D58: Yes | E58: 156250
A60: =A57+1 -> 11 | B60: Security | C60: CKR | D60: Yes | E60: 82500 | G60: 0 | H60: =G60*$H$2 -> 0 | I60: =G60*$I$2 -> 0 | J60: =G60*$J$2 -> 0 | K60: =G60*$K$2 -> 0 | L60: =G60*$L$2 -> 0 | M60: =SUM(H60:L60) -> 0 | O60: =M60+N60 -> 0 | W60: 29
C61: Jensen Hughes | D61: Yes | E61: 94650 | M61: =SUM(H61:L61) -> 0 | O61: =M61+N61 -> 0 | W61: =SUM(W57:W60) -> 323
A63: =A60+1 -> 12 | B63: Telecom (AV/ICT) | C63: Emaar Tech | D63: Yes | E63: 72000 | H63: =G63*$H$2 -> 0 | I63: =G63*$I$2 -> 0 | J63: =G63*$J$2 -> 0 | K63: =G63*$K$2 -> 0 | L63: =G63*$L$2 -> 0 | M63: =SUM(H63:L63) -> 0 | O63: =M63+N63 -> 0
M64: =SUM(H64:L64) -> 0 | O64: =M64+N64 -> 0
A65: =A63+1 -> 13 | B65: Pools & Water Specialist | C65: Barr + Wray | H65: =G65*$H$2 -> 0 | I65: =G65*$I$2 -> 0 | J65: =G65*$J$2 -> 0 | K65: =G65*$K$2 -> 0 | L65: =G65*$L$2 -> 0 | M65: =SUM(H65:L65) -> 0 | O65: =M65+N65 -> 0
C66: Starpool | M66: =SUM(H66:L66) -> 0 | O66: =M66+N66 -> 0
C67: The Wellness | D67: Yes | M67: =SUM(H67:L67) -> 0 | O67: =M67+N67 -> 0
C68: EME | D68: Yes
A70: =A65+1 -> 14 | B70: Fire Life Study | C70: Vortex | D70: Yes | E70: 72500 | H70: =G70*$H$2 -> 0 | I70: =G70*$I$2 -> 0 | J70: =G70*$J$2 -> 0 | K70: =G70*$K$2 -> 0 | L70: =G70*$L$2 -> 0 | M70: =SUM(H70:L70) -> 0 | O70: =M70+N70 -> 0
C71: Design Confidence | D71: Yes | E71: 150000
C72: Jensen Hughes | D72: Yes | E72: 175000
C73: AESG | D73: Yes | E73: 240000
X74: 30000
A75: =A70+1 -> 15 | B75: Vertical Transportation | C75: Barker Mohandas | D75: Yes | H75: =G75*$H$2 -> 0 | I75: =G75*$I$2 -> 0 | J75: =G75*$J$2 -> 0 | K75: =G75*$K$2 -> 0 | L75: =G75*$L$2 -> 0 | M75: =SUM(H75:L75) -> 0 | O75: =M75+N75 -> 0 | X75: 25000
C76: RBA Vertical Transportation Consultants | D76: Yes | M76: =SUM(H76:L76) -> 0 | O76: =M76+N76 -> 0 | X76: 25000
A78: =A75+1 -> 16 | B78: Traffic Impact Study | C78: Zutari | E78: Declined | H78: =G78*$H$2 -> 0 | I78: =G78*$I$2 -> 0 | J78: =G78*$J$2 -> 0 | K78: =G78*$K$2 -> 0 | L78: =G78*$L$2 -> 0 | M78: =SUM(H78:L78) -> 0 | O78: =M78+N78 -> 0 | X78: 12500
C79: Al Turath | D79: Yes | X79: 5000
C80: Infracad
C81: CDM Smith | D81: Yes
C82: Transpo
A84: =A78+1 -> 17 | B84: Acoustics | C84: Inhabit | D84: Yes | E84: 58000 | H84: =G84*$H$2 -> 0 | I84: =G84*$I$2 -> 0 | J84: =G84*$J$2 -> 0 | K84: =G84*$K$2 -> 0 | L84: =G84*$L$2 -> 0 | M84: =SUM(H84:L84) -> 0 | O84: =M84+N84 -> 0 | X84: =SUM(X74:X79) -> 97500
C85: Ramboll
C86: DARL | D86: Yes | E86: 78000 + 15500
C87: AESG | E87: 112000
A89: =A84+1 -> 18 | B89: 3rd Party Structural Peer Review | C89: Qualiconsult | H89: =G89*$H$2 -> 0 | I89: =G89*$I$2 -> 0 | J89: =G89*$J$2 -> 0 | K89: =G89*$K$2 -> 0 | L89: =G89*$L$2 -> 0 | M89: =SUM(H89:L89) -> 0 | O89: =M89+N89 -> 0
C90: SSE | D90: Yes
O91: =M91+N91 -> 0
A92: =A89+1 -> 19 | B92: 3rd Party Geotechnical Peer Review | C92: Qualiconsult | H92: =G92*$H$2 -> 0 | I92: =G92*$I$2 -> 0 | J92: =G92*$J$2 -> 0 | K92: =G92*$K$2 -> 0 | L92: =G92*$L$2 -> 0 | M92: =SUM(H92:L92) -> 0 | O92: =M92+N92 -> 0
C93: SSE | D93: Yes
O94: =M94+N94 -> 0
A95: =A92+1 -> 20 | B95: Aeronautical | C95: Nortech | D95: Yes | E95: 16040 | H95: =G95*$H$2 -> 0 | I95: =G95*$I$2 -> 0 | J95: =G95*$J$2 -> 0 | K95: =G95*$K$2 -> 0 | L95: =G95*$L$2 -> 0 | M95: =SUM(H95:L95) -> 0 | O95: =M95+N95 -> 0
A97: =A95+1 -> 21 | B97: DMGBC / Al Sa’fat Green Building Facilitation | C97: PSDI | D97: Yes | E97: 40500 | H97: =G97*$H$2 -> 0 | I97: =G97*$I$2 -> 0 | J97: =G97*$J$2 -> 0 | K97: =G97*$K$2 -> 0 | L97: =G97*$L$2 -> 0 | M97: =SUM(H97:L97) -> 0 | O97: =M97+N97 -> 0
M98: =SUM(H98:L98) -> 0
B99: Waste Management | C99: CDS | D99: Yes
C100: MCTS | D100: Yes | E100: 118200
B102: Soil Investigation | C102: By Client | H102: =G102*$H$2 -> 0 | I102: =G102*$I$2 -> 0 | J102: =G102*$J$2 -> 0 | K102: =G102*$K$2 -> 0 | L102: =G102*$L$2 -> 0 | M102: =SUM(H102:L102) -> 0 | O102: =M102+N102 -> 0
A103: =A97+1 -> 22 | B103: Topographical Survey | C103: By Client | H103: =G103*$H$2 -> 0 | I103: =G103*$I$2 -> 0 | J103: =G103*$J$2 -> 0 | K103: =G103*$K$2 -> 0 | L103: =G103*$L$2 -> 0 | M103: =SUM(H103:L103) -> 0 | O103: =M103+N103 -> 0
B104: External Renderings | C104: By Client
B105: Environmental Impact Study | C105: By Client | H105: =G105*$H$2 -> 0 | I105: =G105*$I$2 -> 0 | J105: =G105*$J$2 -> 0 | K105: =G105*$K$2 -> 0 | L105: =G105*$L$2 -> 0
A106: =A103+1 -> 23 | B106: Misc. Budget - Subs | H106: =G106*$H$2 -> 0 | I106: =G106*$I$2 -> 0 | J106: =G106*$J$2 -> 0 | K106: =G106*$K$2 -> 0 | L106: =G106*$L$2 -> 0 | M106: =SUM(H106:L106) -> 0 | O106: =M106+N106 -> 0
A107: =A106+1 -> 24 | B107: TOTAL SUB-CONSULTANT FEE (INCL CONT) | F107: =SUM(F13:F106) -> 10037552 | G107: =SUM(G13:G106) -> 10570565 | H107: =SUM(H13:H106) -> 2081250 | I107: =SUM(I13:I106) -> 2497500 | J107: =SUM(J13:J106) -> 2913750 | K107: =SUM(K13:K106) -> 416250 | L107: =SUM(L13:L106) -> 416250 | M107: =SUM(M13:M106) -> 8325000 | ... O107: =SUM(O13:O106) -> 8325000
A108: =A107+1 -> 25 | B108: Architecture & Project Manager (Mirage Design) | C108: Mirage | F108: 2000000 | G108: 2000000 | H108: =G108*$H$2 -> 500000 | I108: =G108*$I$2 -> 600000 | J108: =G108*$J$2 -> 700000 | K108: =G108*$K$2 -> 100000 | L108: =G108*$L$2 -> 100000 | M108: =SUM(H108:L108) -> 2000000 | O108: =M108+N108 -> 2000000
A109: =A108+1 -> 26 | B109: Structures | C109: Mirage | F109: 2500000 | G109: 2500000 | H109: =G109*$H$2 -> 625000 | I109: =G109*$I$2 -> 750000 | J109: =G109*$J$2 -> 875000 | K109: =G109*$K$2 -> 125000 | L109: =G109*$L$2 -> 125000 | M109: =SUM(H109:L109) -> 2500000 | O109: =M109+N109 -> 2500000
A110: =A109+1 -> 27 | B110: Landscape | C110: Mirage
A111: =A110+1 -> 28 | B111: Design support during Construction - Mirage | C111: Mirage | H111: =G111*$H$2 -> 0 | I111: =G111*$I$2 -> 0 | J111: =G111*$J$2 -> 0 | K111: =G111*$K$2 -> 0 | L111: =G111*$L$2 -> 0 | M111: =SUM(H111:L111) -> 0 | O111: =M111+N111 -> 0
A112: =A111+1 -> 29 | B112: Direct Costs (Aconex, PI Insurance, etc) Other Misc. Expenses | C112: Mirage | F112: 100000 | G112: 100000 | H112: =G112*$H$2 -> 25000 | I112: =G112*$I$2 -> 30000 | J112: =G112*$J$2 -> 35000 | K112: =G112*$K$2 -> 5000 | L112: =G112*$L$2 -> 5000 | M112: =SUM(H112:L112) -> 100000 | O112: =M112+N112 -> 100000
O113: =M113+N113 -> 0
B114: TOTAL FEE FOR COMPONENT | F114: =SUM(F107:F113) -> 14637552 | G114: =SUM(G107:G113) -> 15170565 | H114: =SUM(H107:H113) -> 3231250 | I114: =SUM(I107:I113) -> 3877500 | J114: =SUM(J107:J113) -> 4523750 | K114: =SUM(K107:K113) -> 646250 | L114: =SUM(L107:L113) -> 646250 | M114: =SUM(M107:M113) -> 12925000 | ... O114: =SUM(O107:O113) -> 12925000
B115: Design Contingency @15% | F115: =F114*15% -> 2195632.9 | G115: =G114*15% -> 2275584.8 | H115: =G115*$H$2 -> 568896.19 | I115: =G115*$I$2 -> 682675.42 | J115: =G115*$J$2 -> 796454.66 | K115: =G115*$K$2 -> 113779.24 | L115: =G115*$L$2 -> 113779.24 | M115: =SUM(H115:L115) -> 2275584.7 | O115: =M115+N115 -> 2275584.7
B116: TOTAL MARGIN @ 10% | F116: =P118 -> 0 | G116: =R118 -> 1938461.1 | H116: =G116*$H$2 -> 484615.27 | I116: =G116*$I$2 -> 581538.32 | J116: =G116*$J$2 -> 678461.38 | K116: =G116*$K$2 -> 96923.054 | L116: =G116*$L$2 -> 96923.054 | M116: =SUM(H116:L116) -> 1938461.1 | O116: =M116+N116 -> 1938461.1 | R116: =G114+G115 -> 17446150
B117: TOTAL DESIGN | F117: =SUM(F114:F116) -> 16833185 | G117: =SUM(G114:G116) -> 19384611 | H117: =SUM(H114:H116) -> 4284761.5 | I117: =SUM(I114:I116) -> 5141713.8 | J117: =SUM(J114:J116) -> 5998666 | K117: =SUM(K114:K116) -> 856952.29 | L117: =SUM(L114:L116) -> 856952.29 | M117: =SUM(M114:M116) -> 17139046 | ... O117: =SUM(O114:O116) -> 17139046 | R117: =R116/0.9 -> 19384611
H118: 0.25 | I118: 0.3 | J118: 0.35 | K118: 0.05 | L118: 0.05 | R118: =R117*10% -> 1938461.1
H120: 0.2 | I120: 0.3 | J120: 0.35 | K120: 0.1 | L120: 0.05
H122: 1522419.8 | I122: 1826903.7 | J122: 2131387.7 | K122: 304483.96 | L122: 304483.96 | M122: 6089679.1
H123: =H120*$M$122 -> 1217935.8 | I123: =I120*$M$122 -> 1826903.7 | J123: =J120*$M$122 -> 2131387.7 | K123: =K120*$M$122 -> 608967.91 | L123: =L120*$M$122 -> 304483.96

Sheet Mastersheet-Resources
C3: RESOURCING FORECAST FOR BVLGARI, DCG, SE-01/SW-01, AMR EW-8. EW-09, EW-06 & F14 | I3: 46195 | J3: =I3+7 -> 46202 | K3: =J3+7 -> 46209 | L3: =K3+7 -> 46216 | M3: =L3+7 -> 46223 | N3: =M3+7 -> 46230 | O3: =N3+7 -> 46237 | P3: =O3+7 -> 46244 | Q3: =P3+7 -> 46251 | ... BG3: =BF3+7 -> 46545
A4: # | B4: Staff Name | C4: Code | D4: Staff Role | E4: Current Resources | F4: Resource Projection | G4: FWA Resource | H4: Average Resource Required (till Nov end) | I4: W47 | J4: W48 | K4: W49 | L4: W50 | M4: W51 | N4: W52 | O4: W53 | P4: W54 | Q4: W55 | R4: W56 | S4: W57 | T4: W58 | U4: W59 | V4: W60 | W4: W61 | X4: W62 | Y4: W63 | Z4: W64 | AA4: W65 | AB4: W66 | AC4: W67 | AD4: W68 | AE4: W69 | AF4: W70 | AG4: W71 | AH4: W72 | AI4: W73 | AJ4: W74 | AK4: W75 | AL4: W76 | AM4: W77 | AN4: W78 | AO4: W79 | AP4: W80 | AQ4: W81 | AR4: W82 | AS4: W83 | AT4: W84 | AU4: W85 | AV4: W86 | AW4: W87 | AX4: W87 | AY4: W87 | AZ4: W87 | BA4: W87 | BB4: W87 | BC4: W87 | BD4: W87 | BE4: W87 | BF4: W87 | BG4: W87
C5: MEP | D5: MEP Director | E5: 1 | F5: 1 | G5: 1 | H5: =AVERAGE(X5:AO5) -> 0.24444444 | I5: =SUMIF('Mastersheet-Projects'!$B$41:$B$68,$C5,'Mastersheet-Projects'!E$41:E$68)/45 -> 0 | J5: =SUMIF('Mastersheet-Projects'!$B$41:$B$68,$C5,'Mastersheet-Projects'!F$41:F$68)/45 -> 0 | K5: =SUMIF('Mastersheet-Projects'!$B$41:$B$68,$C5,'Mastersheet-Projects'!G$41:G$68)/45 -> 0 | L5: =SUMIF('Mastersheet-Projects'!$B$41:$B$68,$C5,'Mastersheet-Projects'!H$41:H$68)/45 -> 0 | M5: =SUMIF('Mastersheet-Projects'!$B$41:$B$68,$C5,'Mastersheet-Projects'!I$41:I$68)/45 -> 0 | N5: =SUMIF('Mastersheet-Projects'!$B$41:$B$68,$C5,'Mastersheet-Projects'!J$41:J$68)/45 -> 0 | O5: =SUMIF('Mastersheet-Projects'!$B$41:$B$68,$C5,'Mastersheet-Projects'!K$41:K$68)/45 -> 0 | P5: =SUMIF('Mastersheet-Projects'!$B$41:$B$68,$C5,'Mastersheet-Projects'!L$41:L$68)/45 -> 0 | ... BG5: =SUMIF('Mastersheet-Projects'!$B$41:$B$68,$C5,'Mastersheet-Projects'!BC$41:BC$68)/45 -> 0
C6: LME | D6: Lead Mech Engr - Dubai | E6: 1 | F6: 1 | G6: 1 | H6: =AVERAGE(X6:AO6) -> 0.17777778 | I6: =SUMIF('Mastersheet-Projects'!$B$41:$B$68,$C6,'Mastersheet-Projects'!E$41:E$68)/45 -> 0 | J6: =SUMIF('Mastersheet-Projects'!$B$41:$B$68,$C6,'Mastersheet-Projects'!F$41:F$68)/45 -> 0 | K6: =SUMIF('Mastersheet-Projects'!$B$41:$B$68,$C6,'Mastersheet-Projects'!G$41:G$68)/45 -> 0 | L6: =SUMIF('Mastersheet-Projects'!$B$41:$B$68,$C6,'Mastersheet-Projects'!H$41:H$68)/45 -> 0 | M6: =SUMIF('Mastersheet-Projects'!$B$41:$B$68,$C6,'Mastersheet-Projects'!I$41:I$68)/45 -> 0 | N6: =SUMIF('Mastersheet-Projects'!$B$41:$B$68,$C6,'Mastersheet-Projects'!J$41:J$68)/45 -> 0 | O6: =SUMIF('Mastersheet-Projects'!$B$41:$B$68,$C6,'Mastersheet-Projects'!K$41:K$68)/45 -> 0 | P6: =SUMIF('Mastersheet-Projects'!$B$41:$B$68,$C6,'Mastersheet-Projects'!L$41:L$68)/45 -> 0 | ... BG6: =SUMIF('Mastersheet-Projects'!$B$41:$B$68,$C6,'Mastersheet-Projects'!BC$41:BC$68)/45 -> 0
C7: LPE | D7: Lead PHE Engr - Dubai | E7: 1 | F7: 1 | G7: 1 | H7: =AVERAGE(X7:AO7) -> 0.17777778 | I7: =SUMIF('Mastersheet-Projects'!$B$41:$B$68,$C7,'Mastersheet-Projects'!E$41:E$68)/45 -> 0 | J7: =SUMIF('Mastersheet-Projects'!$B$41:$B$68,$C7,'Mastersheet-Projects'!F$41:F$68)/45 -> 0 | K7: =SUMIF('Mastersheet-Projects'!$B$41:$B$68,$C7,'Mastersheet-Projects'!G$41:G$68)/45 -> 0 | L7: =SUMIF('Mastersheet-Projects'!$B$41:$B$68,$C7,'Mastersheet-Projects'!H$41:H$68)/45 -> 0 | M7: =SUMIF('Mastersheet-Projects'!$B$41:$B$68,$C7,'Mastersheet-Projects'!I$41:I$68)/45 -> 0 | N7: =SUMIF('Mastersheet-Projects'!$B$41:$B$68,$C7,'Mastersheet-Projects'!J$41:J$68)/45 -> 0 | O7: =SUMIF('Mastersheet-Projects'!$B$41:$B$68,$C7,'Mastersheet-Projects'!K$41:K$68)/45 -> 0 | P7: =SUMIF('Mastersheet-Projects'!$B$41:$B$68,$C7,'Mastersheet-Projects'!L$41:L$68)/45 -> 0 | ... BG7: =SUMIF('Mastersheet-Projects'!$B$41:$B$68,$C7,'Mastersheet-Projects'!BC$41:BC$68)/45 -> 0
A8: 3 | C8: LEE | D8: Lead Elect Engr - Dubai | E8: 1 | F8: 1 | G8: 1 | H8: =AVERAGE(X8:AO8) -> 0.17777778 | I8: =SUMIF('Mastersheet-Projects'!$B$41:$B$68,$C8,'Mastersheet-Projects'!E$41:E$68)/45 -> 0 | J8: =SUMIF('Mastersheet-Projects'!$B$41:$B$68,$C8,'Mastersheet-Projects'!F$41:F$68)/45 -> 0 | K8: =SUMIF('Mastersheet-Projects'!$B$41:$B$68,$C8,'Mastersheet-Projects'!G$41:G$68)/45 -> 0 | L8: =SUMIF('Mastersheet-Projects'!$B$41:$B$68,$C8,'Mastersheet-Projects'!H$41:H$68)/45 -> 0 | M8: =SUMIF('Mastersheet-Projects'!$B$41:$B$68,$C8,'Mastersheet-Projects'!I$41:I$68)/45 -> 0 | N8: =SUMIF('Mastersheet-Projects'!$B$41:$B$68,$C8,'Mastersheet-Projects'!J$41:J$68)/45 -> 0 | O8: =SUMIF('Mastersheet-Projects'!$B$41:$B$68,$C8,'Mastersheet-Projects'!K$41:K$68)/45 -> 0 | P8: =SUMIF('Mastersheet-Projects'!$B$41:$B$68,$C8,'Mastersheet-Projects'!L$41:L$68)/45 -> 0 | ... BG8: =SUMIF('Mastersheet-Projects'!$B$41:$B$68,$C8,'Mastersheet-Projects'!BC$41:BC$68)/45 -> 0
C9: SMED | D9: Senior Mech Engr - Dubai | F9: 1 | G9: 1 | H9: =AVERAGE(X9:AO9) -> 0 | I9: =SUMIF('Mastersheet-Projects'!$B$41:$B$68,$C9,'Mastersheet-Projects'!E$41:E$68)/45 -> 0 | J9: =SUMIF('Mastersheet-Projects'!$B$41:$B$68,$C9,'Mastersheet-Projects'!F$41:F$68)/45 -> 0 | K9: =SUMIF('Mastersheet-Projects'!$B$41:$B$68,$C9,'Mastersheet-Projects'!G$41:G$68)/45 -> 0 | L9: =SUMIF('Mastersheet-Projects'!$B$41:$B$68,$C9,'Mastersheet-Projects'!H$41:H$68)/45 -> 0 | M9: =SUMIF('Mastersheet-Projects'!$B$41:$B$68,$C9,'Mastersheet-Projects'!I$41:I$68)/45 -> 0 | N9: =SUMIF('Mastersheet-Projects'!$B$41:$B$68,$C9,'Mastersheet-Projects'!J$41:J$68)/45 -> 0 | O9: =SUMIF('Mastersheet-Projects'!$B$41:$B$68,$C9,'Mastersheet-Projects'!K$41:K$68)/45 -> 0 | P9: =SUMIF('Mastersheet-Projects'!$B$41:$B$68,$C9,'Mastersheet-Projects'!L$41:L$68)/45 -> 0 | ... BG9: =SUMIF('Mastersheet-Projects'!$B$41:$B$68,$C9,'Mastersheet-Projects'!BC$41:BC$68)/45 -> 0
C10: SPED | D10: Senior PHE Engr - Dubai | E10: 1 | F10: 1 | G10: 1 | H10: =AVERAGE(X10:AO10) -> 0 | I10: =SUMIF('Mastersheet-Projects'!$B$41:$B$68,$C10,'Mastersheet-Projects'!E$41:E$68)/45 -> 0 | J10: =SUMIF('Mastersheet-Projects'!$B$41:$B$68,$C10,'Mastersheet-Projects'!F$41:F$68)/45 -> 0 | K10: =SUMIF('Mastersheet-Projects'!$B$41:$B$68,$C10,'Mastersheet-Projects'!G$41:G$68)/45 -> 0 | L10: =SUMIF('Mastersheet-Projects'!$B$41:$B$68,$C10,'Mastersheet-Projects'!H$41:H$68)/45 -> 0 | M10: =SUMIF('Mastersheet-Projects'!$B$41:$B$68,$C10,'Mastersheet-Projects'!I$41:I$68)/45 -> 0 | N10: =SUMIF('Mastersheet-Projects'!$B$41:$B$68,$C10,'Mastersheet-Projects'!J$41:J$68)/45 -> 0 | O10: =SUMIF('Mastersheet-Projects'!$B$41:$B$68,$C10,'Mastersheet-Projects'!K$41:K$68)/45 -> 0 | P10: =SUMIF('Mastersheet-Projects'!$B$41:$B$68,$C10,'Mastersheet-Projects'!L$41:L$68)/45 -> 0 | ... BG10: =SUMIF('Mastersheet-Projects'!$B$41:$B$68,$C10,'Mastersheet-Projects'!BC$41:BC$68)/45 -> 0
A11: 3 | C11: SEED | D11: Senior Elect Engr - Dubai | F11: 1 | G11: 1 | H11: =AVERAGE(X11:AO11) -> 0 | I11: =SUMIF('Mastersheet-Projects'!$B$41:$B$68,$C11,'Mastersheet-Projects'!E$41:E$68)/45 -> 0 | J11: =SUMIF('Mastersheet-Projects'!$B$41:$B$68,$C11,'Mastersheet-Projects'!F$41:F$68)/45 -> 0 | K11: =SUMIF('Mastersheet-Projects'!$B$41:$B$68,$C11,'Mastersheet-Projects'!G$41:G$68)/45 -> 0 | L11: =SUMIF('Mastersheet-Projects'!$B$41:$B$68,$C11,'Mastersheet-Projects'!H$41:H$68)/45 -> 0 | M11: =SUMIF('Mastersheet-Projects'!$B$41:$B$68,$C11,'Mastersheet-Projects'!I$41:I$68)/45 -> 0 | N11: =SUMIF('Mastersheet-Projects'!$B$41:$B$68,$C11,'Mastersheet-Projects'!J$41:J$68)/45 -> 0 | O11: =SUMIF('Mastersheet-Projects'!$B$41:$B$68,$C11,'Mastersheet-Projects'!K$41:K$68)/45 -> 0 | P11: =SUMIF('Mastersheet-Projects'!$B$41:$B$68,$C11,'Mastersheet-Projects'!L$41:L$68)/45 -> 0 | ... BG11: =SUMIF('Mastersheet-Projects'!$B$41:$B$68,$C11,'Mastersheet-Projects'!BC$41:BC$68)/45 -> 0
C12: AME | D12: Principal Mech Engr | E12: 1 | F12: 1 | G12: 1 | H12: =AVERAGE(X12:AO12) -> 0 | I12: =SUMIF('Mastersheet-Projects'!$B$41:$B$68,$C12,'Mastersheet-Projects'!E$41:E$68)/45 -> 0 | J12: =SUMIF('Mastersheet-Projects'!$B$41:$B$68,$C12,'Mastersheet-Projects'!F$41:F$68)/45 -> 0 | K12: =SUMIF('Mastersheet-Projects'!$B$41:$B$68,$C12,'Mastersheet-Projects'!G$41:G$68)/45 -> 0 | L12: =SUMIF('Mastersheet-Projects'!$B$41:$B$68,$C12,'Mastersheet-Projects'!H$41:H$68)/45 -> 0 | M12: =SUMIF('Mastersheet-Projects'!$B$41:$B$68,$C12,'Mastersheet-Projects'!I$41:I$68)/45 -> 0 | N12: =SUMIF('Mastersheet-Projects'!$B$41:$B$68,$C12,'Mastersheet-Projects'!J$41:J$68)/45 -> 0 | O12: =SUMIF('Mastersheet-Projects'!$B$41:$B$68,$C12,'Mastersheet-Projects'!K$41:K$68)/45 -> 0 | P12: =SUMIF('Mastersheet-Projects'!$B$41:$B$68,$C12,'Mastersheet-Projects'!L$41:L$68)/45 -> 0 | ... BG12: =SUMIF('Mastersheet-Projects'!$B$41:$B$68,$C12,'Mastersheet-Projects'!BC$41:BC$68)/45 -> 0
A13: 3 | C13: SME | D13: Senior Mechanical Engineer | E13: 1 | F13: 1 | G13: 1 | H13: =AVERAGE(X13:AO13) -> 0.55555556 | I13: =SUMIF('Mastersheet-Projects'!$B$41:$B$68,$C13,'Mastersheet-Projects'!E$41:E$68)/45 -> 0 | J13: =SUMIF('Mastersheet-Projects'!$B$41:$B$68,$C13,'Mastersheet-Projects'!F$41:F$68)/45 -> 0 | K13: =SUMIF('Mastersheet-Projects'!$B$41:$B$68,$C13,'Mastersheet-Projects'!G$41:G$68)/45 -> 0 | L13: =SUMIF('Mastersheet-Projects'!$B$41:$B$68,$C13,'Mastersheet-Projects'!H$41:H$68)/45 -> 0 | M13: =SUMIF('Mastersheet-Projects'!$B$41:$B$68,$C13,'Mastersheet-Projects'!I$41:I$68)/45 -> 0 | N13: =SUMIF('Mastersheet-Projects'!$B$41:$B$68,$C13,'Mastersheet-Projects'!J$41:J$68)/45 -> 0 | O13: =SUMIF('Mastersheet-Projects'!$B$41:$B$68,$C13,'Mastersheet-Projects'!K$41:K$68)/45 -> 0 | P13: =SUMIF('Mastersheet-Projects'!$B$41:$B$68,$C13,'Mastersheet-Projects'!L$41:L$68)/45 -> 0 | ... BG13: =SUMIF('Mastersheet-Projects'!$B$41:$B$68,$C13,'Mastersheet-Projects'!BC$41:BC$68)/45 -> 0
A14: 4 | C14: JME | D14: Mechanical Engineer | E14: 2 | F14: 5 | G14: 5 | H14: =AVERAGE(X14:AO14) -> 0.98148148 | I14: =SUMIF('Mastersheet-Projects'!$B$41:$B$68,$C14,'Mastersheet-Projects'!E$41:E$68)/45 -> 0 | J14: =SUMIF('Mastersheet-Projects'!$B$41:$B$68,$C14,'Mastersheet-Projects'!F$41:F$68)/45 -> 0 | K14: =SUMIF('Mastersheet-Projects'!$B$41:$B$68,$C14,'Mastersheet-Projects'!G$41:G$68)/45 -> 0 | L14: =SUMIF('Mastersheet-Projects'!$B$41:$B$68,$C14,'Mastersheet-Projects'!H$41:H$68)/45 -> 0 | M14: =SUMIF('Mastersheet-Projects'!$B$41:$B$68,$C14,'Mastersheet-Projects'!I$41:I$68)/45 -> 0 | N14: =SUMIF('Mastersheet-Projects'!$B$41:$B$68,$C14,'Mastersheet-Projects'!J$41:J$68)/45 -> 0 | O14: =SUMIF('Mastersheet-Projects'!$B$41:$B$68,$C14,'Mastersheet-Projects'!K$41:K$68)/45 -> 0 | P14: =SUMIF('Mastersheet-Projects'!$B$41:$B$68,$C14,'Mastersheet-Projects'!L$41:L$68)/45 -> 0 | ... BG14: =SUMIF('Mastersheet-Projects'!$B$41:$B$68,$C14,'Mastersheet-Projects'!BC$41:BC$68)/45 -> 0
A15: 5 | C15: SPE | D15: Senior PHE Engr | F15: 1 | G15: 1 | H15: =AVERAGE(X15:AO15) -> 0.55555556 | I15: =SUMIF('Mastersheet-Projects'!$B$41:$B$68,$C15,'Mastersheet-Projects'!E$41:E$68)/45 -> 0 | J15: =SUMIF('Mastersheet-Projects'!$B$41:$B$68,$C15,'Mastersheet-Projects'!F$41:F$68)/45 -> 0 | K15: =SUMIF('Mastersheet-Projects'!$B$41:$B$68,$C15,'Mastersheet-Projects'!G$41:G$68)/45 -> 0 | L15: =SUMIF('Mastersheet-Projects'!$B$41:$B$68,$C15,'Mastersheet-Projects'!H$41:H$68)/45 -> 0 | M15: =SUMIF('Mastersheet-Projects'!$B$41:$B$68,$C15,'Mastersheet-Projects'!I$41:I$68)/45 -> 0 | N15: =SUMIF('Mastersheet-Projects'!$B$41:$B$68,$C15,'Mastersheet-Projects'!J$41:J$68)/45 -> 0 | O15: =SUMIF('Mastersheet-Projects'!$B$41:$B$68,$C15,'Mastersheet-Projects'!K$41:K$68)/45 -> 0 | P15: =SUMIF('Mastersheet-Projects'!$B$41:$B$68,$C15,'Mastersheet-Projects'!L$41:L$68)/45 -> 0 | ... BG15: =SUMIF('Mastersheet-Projects'!$B$41:$B$68,$C15,'Mastersheet-Projects'!BC$41:BC$68)/45 -> 0
A16: 6 | C16: JPE | D16: PHE Engineer | E16: 2 | F16: 5 | G16: 5 | H16: =AVERAGE(X16:AO16) -> 0.98148148 | I16: =SUMIF('Mastersheet-Projects'!$B$41:$B$68,$C16,'Mastersheet-Projects'!E$41:E$68)/45 -> 0 | J16: =SUMIF('Mastersheet-Projects'!$B$41:$B$68,$C16,'Mastersheet-Projects'!F$41:F$68)/45 -> 0 | K16: =SUMIF('Mastersheet-Projects'!$B$41:$B$68,$C16,'Mastersheet-Projects'!G$41:G$68)/45 -> 0 | L16: =SUMIF('Mastersheet-Projects'!$B$41:$B$68,$C16,'Mastersheet-Projects'!H$41:H$68)/45 -> 0 | M16: =SUMIF('Mastersheet-Projects'!$B$41:$B$68,$C16,'Mastersheet-Projects'!I$41:I$68)/45 -> 0 | N16: =SUMIF('Mastersheet-Projects'!$B$41:$B$68,$C16,'Mastersheet-Projects'!J$41:J$68)/45 -> 0 | O16: =SUMIF('Mastersheet-Projects'!$B$41:$B$68,$C16,'Mastersheet-Projects'!K$41:K$68)/45 -> 0 | P16: =SUMIF('Mastersheet-Projects'!$B$41:$B$68,$C16,'Mastersheet-Projects'!L$41:L$68)/45 -> 0 | ... BG16: =SUMIF('Mastersheet-Projects'!$B$41:$B$68,$C16,'Mastersheet-Projects'!BC$41:BC$68)/45 -> 0
A17: 7 | C17: SEE | D17: Senior Electrical Engineer | E17: 2 | F17: 1 | G17: 1 | H17: =AVERAGE(X17:AO17) -> 0.55555556 | I17: =SUMIF('Mastersheet-Projects'!$B$41:$B$68,$C17,'Mastersheet-Projects'!E$41:E$68)/45 -> 0 | J17: =SUMIF('Mastersheet-Projects'!$B$41:$B$68,$C17,'Mastersheet-Projects'!F$41:F$68)/45 -> 0 | K17: =SUMIF('Mastersheet-Projects'!$B$41:$B$68,$C17,'Mastersheet-Projects'!G$41:G$68)/45 -> 0 | L17: =SUMIF('Mastersheet-Projects'!$B$41:$B$68,$C17,'Mastersheet-Projects'!H$41:H$68)/45 -> 0 | M17: =SUMIF('Mastersheet-Projects'!$B$41:$B$68,$C17,'Mastersheet-Projects'!I$41:I$68)/45 -> 0 | N17: =SUMIF('Mastersheet-Projects'!$B$41:$B$68,$C17,'Mastersheet-Projects'!J$41:J$68)/45 -> 0 | O17: =SUMIF('Mastersheet-Projects'!$B$41:$B$68,$C17,'Mastersheet-Projects'!K$41:K$68)/45 -> 0 | P17: =SUMIF('Mastersheet-Projects'!$B$41:$B$68,$C17,'Mastersheet-Projects'!L$41:L$68)/45 -> 0 | ... BG17: =SUMIF('Mastersheet-Projects'!$B$41:$B$68,$C17,'Mastersheet-Projects'!BC$41:BC$68)/45 -> 0
A18: 8 | C18: JEE | D18: Electrical Engineer | E18: 4 | F18: 5 | G18: 5 | H18: =AVERAGE(X18:AO18) -> 0.98148148 | I18: =SUMIF('Mastersheet-Projects'!$B$41:$B$68,$C18,'Mastersheet-Projects'!E$41:E$68)/45 -> 0 | J18: =SUMIF('Mastersheet-Projects'!$B$41:$B$68,$C18,'Mastersheet-Projects'!F$41:F$68)/45 -> 0 | K18: =SUMIF('Mastersheet-Projects'!$B$41:$B$68,$C18,'Mastersheet-Projects'!G$41:G$68)/45 -> 0 | L18: =SUMIF('Mastersheet-Projects'!$B$41:$B$68,$C18,'Mastersheet-Projects'!H$41:H$68)/45 -> 0 | M18: =SUMIF('Mastersheet-Projects'!$B$41:$B$68,$C18,'Mastersheet-Projects'!I$41:I$68)/45 -> 0 | N18: =SUMIF('Mastersheet-Projects'!$B$41:$B$68,$C18,'Mastersheet-Projects'!J$41:J$68)/45 -> 0 | O18: =SUMIF('Mastersheet-Projects'!$B$41:$B$68,$C18,'Mastersheet-Projects'!K$41:K$68)/45 -> 0 | P18: =SUMIF('Mastersheet-Projects'!$B$41:$B$68,$C18,'Mastersheet-Projects'!L$41:L$68)/45 -> 0 | ... BG18: =SUMIF('Mastersheet-Projects'!$B$41:$B$68,$C18,'Mastersheet-Projects'!BC$41:BC$68)/45 -> 0
A19: 9 | C19: BL | D19: BIM Manager/Coordinator | E19: 2 | F19: 2 | G19: 2 | H19: =AVERAGE(X19:AO19) -> 0.35555556 | I19: =SUMIF('Mastersheet-Projects'!$B$41:$B$68,$C19,'Mastersheet-Projects'!E$41:E$68)/45 -> 0 | J19: =SUMIF('Mastersheet-Projects'!$B$41:$B$68,$C19,'Mastersheet-Projects'!F$41:F$68)/45 -> 0 | K19: =SUMIF('Mastersheet-Projects'!$B$41:$B$68,$C19,'Mastersheet-Projects'!G$41:G$68)/45 -> 0 | L19: =SUMIF('Mastersheet-Projects'!$B$41:$B$68,$C19,'Mastersheet-Projects'!H$41:H$68)/45 -> 0 | M19: =SUMIF('Mastersheet-Projects'!$B$41:$B$68,$C19,'Mastersheet-Projects'!I$41:I$68)/45 -> 0 | N19: =SUMIF('Mastersheet-Projects'!$B$41:$B$68,$C19,'Mastersheet-Projects'!J$41:J$68)/45 -> 0 | O19: =SUMIF('Mastersheet-Projects'!$B$41:$B$68,$C19,'Mastersheet-Projects'!K$41:K$68)/45 -> 0 | P19: =SUMIF('Mastersheet-Projects'!$B$41:$B$68,$C19,'Mastersheet-Projects'!L$41:L$68)/45 -> 0 | ... BG19: =SUMIF('Mastersheet-Projects'!$B$41:$B$68,$C19,'Mastersheet-Projects'!BC$41:BC$68)/45 -> 0
A20: 13 | C20: BML | D20: BIM Lead-M | E20: 1 | F20: 2 | G20: 1 | H20: =AVERAGE(X20:AO20) -> 0.53333333 | I20: =SUMIF('Mastersheet-Projects'!$B$41:$B$68,$C20,'Mastersheet-Projects'!E$41:E$68)/45 -> 0 | J20: =SUMIF('Mastersheet-Projects'!$B$41:$B$68,$C20,'Mastersheet-Projects'!F$41:F$68)/45 -> 0 | K20: =SUMIF('Mastersheet-Projects'!$B$41:$B$68,$C20,'Mastersheet-Projects'!G$41:G$68)/45 -> 0 | L20: =SUMIF('Mastersheet-Projects'!$B$41:$B$68,$C20,'Mastersheet-Projects'!H$41:H$68)/45 -> 0 | M20: =SUMIF('Mastersheet-Projects'!$B$41:$B$68,$C20,'Mastersheet-Projects'!I$41:I$68)/45 -> 0 | N20: =SUMIF('Mastersheet-Projects'!$B$41:$B$68,$C20,'Mastersheet-Projects'!J$41:J$68)/45 -> 0 | O20: =SUMIF('Mastersheet-Projects'!$B$41:$B$68,$C20,'Mastersheet-Projects'!K$41:K$68)/45 -> 0 | P20: =SUMIF('Mastersheet-Projects'!$B$41:$B$68,$C20,'Mastersheet-Projects'!L$41:L$68)/45 -> 0 | ... BG20: =SUMIF('Mastersheet-Projects'!$B$41:$B$68,$C20,'Mastersheet-Projects'!BC$41:BC$68)/45 -> 0
A21: 10 | C21: BM | D21: BIM Modeller-M | E21: 14 | F21: 20 | G21: 12 | H21: =AVERAGE(X21:AO21) -> 2.3333333 | I21: =SUMIF('Mastersheet-Projects'!$B$41:$B$68,$C21,'Mastersheet-Projects'!E$41:E$68)/45 -> 0 | J21: =SUMIF('Mastersheet-Projects'!$B$41:$B$68,$C21,'Mastersheet-Projects'!F$41:F$68)/45 -> 0 | K21: =SUMIF('Mastersheet-Projects'!$B$41:$B$68,$C21,'Mastersheet-Projects'!G$41:G$68)/45 -> 0 | L21: =SUMIF('Mastersheet-Projects'!$B$41:$B$68,$C21,'Mastersheet-Projects'!H$41:H$68)/45 -> 0 | M21: =SUMIF('Mastersheet-Projects'!$B$41:$B$68,$C21,'Mastersheet-Projects'!I$41:I$68)/45 -> 0 | N21: =SUMIF('Mastersheet-Projects'!$B$41:$B$68,$C21,'Mastersheet-Projects'!J$41:J$68)/45 -> 0 | O21: =SUMIF('Mastersheet-Projects'!$B$41:$B$68,$C21,'Mastersheet-Projects'!K$41:K$68)/45 -> 0 | P21: =SUMIF('Mastersheet-Projects'!$B$41:$B$68,$C21,'Mastersheet-Projects'!L$41:L$68)/45 -> 0 | ... BG21: =SUMIF('Mastersheet-Projects'!$B$41:$B$68,$C21,'Mastersheet-Projects'!BC$41:BC$68)/45 -> 0
A22: 13 | C22: BJM | D22: Junior BIM Modeller-M | E22: 4 | F22: 2 | G22: 1 | H22: =AVERAGE(X22:AO22) -> 0.77777778 | I22: =SUMIF('Mastersheet-Projects'!$B$41:$B$68,$C22,'Mastersheet-Projects'!E$41:E$68)/45 -> 0 | J22: =SUMIF('Mastersheet-Projects'!$B$41:$B$68,$C22,'Mastersheet-Projects'!F$41:F$68)/45 -> 0 | K22: =SUMIF('Mastersheet-Projects'!$B$41:$B$68,$C22,'Mastersheet-Projects'!G$41:G$68)/45 -> 0 | L22: =SUMIF('Mastersheet-Projects'!$B$41:$B$68,$C22,'Mastersheet-Projects'!H$41:H$68)/45 -> 0 | M22: =SUMIF('Mastersheet-Projects'!$B$41:$B$68,$C22,'Mastersheet-Projects'!I$41:I$68)/45 -> 0 | N22: =SUMIF('Mastersheet-Projects'!$B$41:$B$68,$C22,'Mastersheet-Projects'!J$41:J$68)/45 -> 0 | O22: =SUMIF('Mastersheet-Projects'!$B$41:$B$68,$C22,'Mastersheet-Projects'!K$41:K$68)/45 -> 0 | P22: =SUMIF('Mastersheet-Projects'!$B$41:$B$68,$C22,'Mastersheet-Projects'!L$41:L$68)/45 -> 0 | ... BG22: =SUMIF('Mastersheet-Projects'!$B$41:$B$68,$C22,'Mastersheet-Projects'!BC$41:BC$68)/45 -> 0
A23: 10 | C23: BPL | D23: BIM Lead-P | E23: 2 | F23: 2 | G23: 1 | H23: =AVERAGE(X23:AO23) -> 0.53333333 | I23: =SUMIF('Mastersheet-Projects'!$B$41:$B$68,$C23,'Mastersheet-Projects'!E$41:E$68)/45 -> 0 | J23: =SUMIF('Mastersheet-Projects'!$B$41:$B$68,$C23,'Mastersheet-Projects'!F$41:F$68)/45 -> 0 | K23: =SUMIF('Mastersheet-Projects'!$B$41:$B$68,$C23,'Mastersheet-Projects'!G$41:G$68)/45 -> 0 | L23: =SUMIF('Mastersheet-Projects'!$B$41:$B$68,$C23,'Mastersheet-Projects'!H$41:H$68)/45 -> 0 | M23: =SUMIF('Mastersheet-Projects'!$B$41:$B$68,$C23,'Mastersheet-Projects'!I$41:I$68)/45 -> 0 | N23: =SUMIF('Mastersheet-Projects'!$B$41:$B$68,$C23,'Mastersheet-Projects'!J$41:J$68)/45 -> 0 | O23: =SUMIF('Mastersheet-Projects'!$B$41:$B$68,$C23,'Mastersheet-Projects'!K$41:K$68)/45 -> 0 | P23: =SUMIF('Mastersheet-Projects'!$B$41:$B$68,$C23,'Mastersheet-Projects'!L$41:L$68)/45 -> 0 | ... BG23: =SUMIF('Mastersheet-Projects'!$B$41:$B$68,$C23,'Mastersheet-Projects'!BC$41:BC$68)/45 -> 0
A24: 13 | C24: BP | D24: BIM Modeller-P | E24: 16 | F24: 20 | G24: 12 | H24: =AVERAGE(X24:AO24) -> 2.3333333 | I24: =SUMIF('Mastersheet-Projects'!$B$41:$B$68,$C24,'Mastersheet-Projects'!E$41:E$68)/45 -> 0 | J24: =SUMIF('Mastersheet-Projects'!$B$41:$B$68,$C24,'Mastersheet-Projects'!F$41:F$68)/45 -> 0 | K24: =SUMIF('Mastersheet-Projects'!$B$41:$B$68,$C24,'Mastersheet-Projects'!G$41:G$68)/45 -> 0 | L24: =SUMIF('Mastersheet-Projects'!$B$41:$B$68,$C24,'Mastersheet-Projects'!H$41:H$68)/45 -> 0 | M24: =SUMIF('Mastersheet-Projects'!$B$41:$B$68,$C24,'Mastersheet-Projects'!I$41:I$68)/45 -> 0 | N24: =SUMIF('Mastersheet-Projects'!$B$41:$B$68,$C24,'Mastersheet-Projects'!J$41:J$68)/45 -> 0 | O24: =SUMIF('Mastersheet-Projects'!$B$41:$B$68,$C24,'Mastersheet-Projects'!K$41:K$68)/45 -> 0 | P24: =SUMIF('Mastersheet-Projects'!$B$41:$B$68,$C24,'Mastersheet-Projects'!L$41:L$68)/45 -> 0 | ... BG24: =SUMIF('Mastersheet-Projects'!$B$41:$B$68,$C24,'Mastersheet-Projects'!BC$41:BC$68)/45 -> 0
A25: 13 | C25: BJP | D25: Junior BIM Modeller-P | E25: 3 | F25: 2 | G25: 1 | H25: =AVERAGE(X25:AO25) -> 0.77777778 | I25: =SUMIF('Mastersheet-Projects'!$B$41:$B$68,$C25,'Mastersheet-Projects'!E$41:E$68)/45 -> 0 | J25: =SUMIF('Mastersheet-Projects'!$B$41:$B$68,$C25,'Mastersheet-Projects'!F$41:F$68)/45 -> 0 | K25: =SUMIF('Mastersheet-Projects'!$B$41:$B$68,$C25,'Mastersheet-Projects'!G$41:G$68)/45 -> 0 | L25: =SUMIF('Mastersheet-Projects'!$B$41:$B$68,$C25,'Mastersheet-Projects'!H$41:H$68)/45 -> 0 | M25: =SUMIF('Mastersheet-Projects'!$B$41:$B$68,$C25,'Mastersheet-Projects'!I$41:I$68)/45 -> 0 | N25: =SUMIF('Mastersheet-Projects'!$B$41:$B$68,$C25,'Mastersheet-Projects'!J$41:J$68)/45 -> 0 | O25: =SUMIF('Mastersheet-Projects'!$B$41:$B$68,$C25,'Mastersheet-Projects'!K$41:K$68)/45 -> 0 | P25: =SUMIF('Mastersheet-Projects'!$B$41:$B$68,$C25,'Mastersheet-Projects'!L$41:L$68)/45 -> 0 | ... BG25: =SUMIF('Mastersheet-Projects'!$B$41:$B$68,$C25,'Mastersheet-Projects'!BC$41:BC$68)/45 -> 0
A26: 13 | C26: BEL | D26: BIM Lead-E | E26: 1 | F26: 2 | G26: 1 | H26: =AVERAGE(X26:AO26) -> 0.53333333 | I26: =SUMIF('Mastersheet-Projects'!$B$41:$B$68,$C26,'Mastersheet-Projects'!E$41:E$68)/45 -> 0 | J26: =SUMIF('Mastersheet-Projects'!$B$41:$B$68,$C26,'Mastersheet-Projects'!F$41:F$68)/45 -> 0 | K26: =SUMIF('Mastersheet-Projects'!$B$41:$B$68,$C26,'Mastersheet-Projects'!G$41:G$68)/45 -> 0 | L26: =SUMIF('Mastersheet-Projects'!$B$41:$B$68,$C26,'Mastersheet-Projects'!H$41:H$68)/45 -> 0 | M26: =SUMIF('Mastersheet-Projects'!$B$41:$B$68,$C26,'Mastersheet-Projects'!I$41:I$68)/45 -> 0 | N26: =SUMIF('Mastersheet-Projects'!$B$41:$B$68,$C26,'Mastersheet-Projects'!J$41:J$68)/45 -> 0 | O26: =SUMIF('Mastersheet-Projects'!$B$41:$B$68,$C26,'Mastersheet-Projects'!K$41:K$68)/45 -> 0 | P26: =SUMIF('Mastersheet-Projects'!$B$41:$B$68,$C26,'Mastersheet-Projects'!L$41:L$68)/45 -> 0 | ... BG26: =SUMIF('Mastersheet-Projects'!$B$41:$B$68,$C26,'Mastersheet-Projects'!BC$41:BC$68)/45 -> 0
A27: 10 | C27: BE | D27: BIM Modeller-E | E27: 13 | F27: 20 | G27: 12 | H27: =AVERAGE(X27:AO27) -> 2.3333333 | I27: =SUMIF('Mastersheet-Projects'!$B$41:$B$68,$C27,'Mastersheet-Projects'!E$41:E$68)/45 -> 0 | J27: =SUMIF('Mastersheet-Projects'!$B$41:$B$68,$C27,'Mastersheet-Projects'!F$41:F$68)/45 -> 0 | K27: =SUMIF('Mastersheet-Projects'!$B$41:$B$68,$C27,'Mastersheet-Projects'!G$41:G$68)/45 -> 0 | L27: =SUMIF('Mastersheet-Projects'!$B$41:$B$68,$C27,'Mastersheet-Projects'!H$41:H$68)/45 -> 0 | M27: =SUMIF('Mastersheet-Projects'!$B$41:$B$68,$C27,'Mastersheet-Projects'!I$41:I$68)/45 -> 0 | N27: =SUMIF('Mastersheet-Projects'!$B$41:$B$68,$C27,'Mastersheet-Projects'!J$41:J$68)/45 -> 0 | O27: =SUMIF('Mastersheet-Projects'!$B$41:$B$68,$C27,'Mastersheet-Projects'!K$41:K$68)/45 -> 0 | P27: =SUMIF('Mastersheet-Projects'!$B$41:$B$68,$C27,'Mastersheet-Projects'!L$41:L$68)/45 -> 0 | ... BG27: =SUMIF('Mastersheet-Projects'!$B$41:$B$68,$C27,'Mastersheet-Projects'!BC$41:BC$68)/45 -> 0
A28: 15 | C28: BJE | D28: Junior BIM Modeller-E | E28: 2 | F28: 2 | G28: 1 | H28: =AVERAGE(X28:AO28) -> 0.77777778 | I28: =SUMIF('Mastersheet-Projects'!$B$41:$B$68,$C28,'Mastersheet-Projects'!E$41:E$68)/45 -> 0 | J28: =SUMIF('Mastersheet-Projects'!$B$41:$B$68,$C28,'Mastersheet-Projects'!F$41:F$68)/45 -> 0 | K28: =SUMIF('Mastersheet-Projects'!$B$41:$B$68,$C28,'Mastersheet-Projects'!G$41:G$68)/45 -> 0 | L28: =SUMIF('Mastersheet-Projects'!$B$41:$B$68,$C28,'Mastersheet-Projects'!H$41:H$68)/45 -> 0 | M28: =SUMIF('Mastersheet-Projects'!$B$41:$B$68,$C28,'Mastersheet-Projects'!I$41:I$68)/45 -> 0 | N28: =SUMIF('Mastersheet-Projects'!$B$41:$B$68,$C28,'Mastersheet-Projects'!J$41:J$68)/45 -> 0 | O28: =SUMIF('Mastersheet-Projects'!$B$41:$B$68,$C28,'Mastersheet-Projects'!K$41:K$68)/45 -> 0 | P28: =SUMIF('Mastersheet-Projects'!$B$41:$B$68,$C28,'Mastersheet-Projects'!L$41:L$68)/45 -> 0 | ... BG28: =SUMIF('Mastersheet-Projects'!$B$41:$B$68,$C28,'Mastersheet-Projects'!BC$41:BC$68)/45 -> 0
E29: =SUM(E5:E28) -> 75 | F29: =SUM(F5:F28) -> 100 | G29: =SUM(G5:G28) -> 70 | H29: =SUM(H5:H28) -> 16.677778 | I29: =SUM(I5:I28) -> 0 | J29: =SUM(J5:J28) -> 0 | K29: =SUM(K5:K28) -> 0 | L29: =SUM(L5:L28) -> 0 | ... BG29: =SUM(BG5:BG28) -> 0
I30: ='Mastersheet-Projects'!E67 -> 0 | J30: ='Mastersheet-Projects'!F67 -> 0 | K30: ='Mastersheet-Projects'!G67 -> 0 | L30: ='Mastersheet-Projects'!H67 -> 0 | M30: ='Mastersheet-Projects'!I67 -> 0 | N30: ='Mastersheet-Projects'!J67 -> 0 | O30: ='Mastersheet-Projects'!K67 -> 0 | P30: ='Mastersheet-Projects'!L67 -> 0 | ... BG30: ='Mastersheet-Projects'!BC67 -> 0

Sheet Mastersheet-Projects
B2: MEP | C2: MEP Director
B3: LMEP | C3: MEP Lead (Dubai)
B4: LME | C4: Lead Mech Engr (Dubai)
B5: LPE | C5: Lead PHE Engr (Dubai)
B6: LEE | C6: Lead Elect Engr (Dubai)
B7: SMED | C7: Senior Mech Engr-Dubai
B8: SPED | C8: Senior PHE Engr-Dubai
B9: SEED | C9: Senior Elect Engr-Dubai
B10: AME | C10: Principal Mech Engr
B11: APE | C11: Principal PHE Engr
B12: AEE | C12: Principal Elect Engr/Director
B13: SPE | C13: Senior PHE Engr
... B35: BJP | C35: Junior BIM Modeller-P
E37: 46195 | F37: =E37+7 -> 46202 | G37: =F37+7 -> 46209 | H37: =G37+7 -> 46216 | I37: =H37+7 -> 46223 | J37: =I37+7 -> 46230 | K37: =J37+7 -> 46237 | L37: =K37+7 -> 46244 | M37: =L37+7 -> 46251 | ... BE37: =BD37+7 -> 46559
A38: # | B38: Code | C38: Staff Role | D38: Total Hours
C39: SE-01/SW-01 | BF39: IFC Documentation Issue
D40: =SUM(D41:D66) -> 21789 | G40: CD | H40: CD | I40: CD | J40: CD | K40: CD | L40: CD | M40: CD | N40: CD | O40: CD | P40: CD | Q40: CD | R40: CD | S40: CD | T40: SD | U40: SD | V40: SD | W40: SD | X40: SD | Y40: SD | Z40: SD | AA40: SD | AB40: SD | AC40: SD | AD40: SD | AE40: SD | AF40: SD | AG40: DD | AH40: DD | AI40: DD | AJ40: DD | AK40: DD | AL40: DD | AM40: DD | AN40: DD | AO40: DD | AP40: DD | AQ40: DD | AR40: DD | AS40: TD | AT40: TD | AU40: TD | AV40: TD | AW40: TD | AX40: TD | AY40: TD | AZ40: TD | BA40: TD | BB40: TD | BC40: TD | BD40: TD | BE40: TD | BF40: IFC | BG40: IFC
A41: 1 | B41: MEP | C41: =VLOOKUP($B41,$B$2:$C$35,COLUMN(B41),FALSE) -> MEP Director | D41: =SUM(E41:CH41) -> 342 | O41: 9 | P41: 9 | Q41: 9 | R41: 9 | S41: 9 | T41: 18 | U41: 9 | V41: 9 | W41: 9 | X41: 18 | Y41: 18 | Z41: 18 | AA41: 9 | AB41: 9 | AC41: 9 | AD41: 9 | AG41: 18 | AH41: 18 | AI41: 9 | AJ41: 9 | AK41: 9 | AL41: 18 | AM41: 18 | AN41: 9 | AO41: 9 | AP41: 9 | AQ41: 18 | AR41: 18
A42: 5 | B42: LPE | C42: =VLOOKUP($B42,$B$2:$C$35,COLUMN(B42),FALSE) -> Lead PHE Engr (Dubai) | D42: =SUM(E42:CH42) -> 207 | T42: 9 | U42: 9 | V42: 9 | W42: 9 | X42: 9 | Y42: 9 | Z42: 9 | AA42: 9 | AB42: 9 | AC42: 9 | AD42: 9 | AG42: 9 | AH42: 9 | AI42: 9 | AJ42: 9 | AK42: 9 | AL42: 9 | AM42: 9 | AN42: 9 | AO42: 9 | AP42: 9 | AQ42: 9 | AR42: 9
A43: 6 | B43: LEE | C43: =VLOOKUP($B43,$B$2:$C$35,COLUMN(B43),FALSE) -> Lead Elect Engr (Dubai) | D43: =SUM(E43:CH43) -> 207 | T43: 9 | U43: 9 | V43: 9 | W43: 9 | X43: 9 | Y43: 9 | Z43: 9 | AA43: 9 | AB43: 9 | AC43: 9 | AD43: 9 | AG43: 9 | AH43: 9 | AI43: 9 | AJ43: 9 | AK43: 9 | AL43: 9 | AM43: 9 | AN43: 9 | AO43: 9 | AP43: 9 | AQ43: 9 | AR43: 9
A44: 7 | B44: LME | C44: =VLOOKUP($B44,$B$2:$C$35,COLUMN(B44),FALSE) -> Lead Mech Engr (Dubai) | D44: =SUM(E44:CH44) -> 207 | T44: 9 | U44: 9 | V44: 9 | W44: 9 | X44: 9 | Y44: 9 | Z44: 9 | AA44: 9 | AB44: 9 | AC44: 9 | AD44: 9 | AG44: 9 | AH44: 9 | AI44: 9 | AJ44: 9 | AK44: 9 | AL44: 9 | AM44: 9 | AN44: 9 | AO44: 9 | AP44: 9 | AQ44: 9 | AR44: 9
A45: 5 | B45: SPE | C45: =VLOOKUP($B45,$B$2:$C$35,COLUMN(B45),FALSE) -> Senior PHE Engr | D45: =SUM(E45:CH45) -> 774 | O45: 22.5 | P45: 22.5 | Q45: 18 | R45: 18 | S45: 18 | T45: 27 | U45: 27 | V45: 27 | W45: 27 | X45: 27 | Y45: 27 | Z45: 27 | AA45: 27 | AB45: 27 | AC45: 27 | AD45: 27 | AE45: 9 | AF45: 9 | AG45: 27 | AH45: 27 | AI45: 27 | AJ45: 27 | AK45: 27 | AL45: 27 | AM45: 45 | AN45: 27 | AO45: 27 | AP45: 27 | AQ45: 27 | AR45: 45
A46: 6 | B46: SEE | C46: =VLOOKUP($B46,$B$2:$C$35,COLUMN(B46),FALSE) -> Senior Electrical Engineer | D46: =SUM(E46:CH46) -> 774 | O46: 22.5 | P46: 22.5 | Q46: 18 | R46: 18 | S46: 18 | T46: 27 | U46: 27 | V46: 27 | W46: 27 | X46: 27 | Y46: 27 | Z46: 27 | AA46: 27 | AB46: 27 | AC46: 27 | AD46: 27 | AE46: 9 | AF46: 9 | AG46: 27 | AH46: 27 | AI46: 27 | AJ46: 27 | AK46: 27 | AL46: 27 | AM46: 45 | AN46: 27 | AO46: 27 | AP46: 27 | AQ46: 27 | AR46: 45
A47: 7 | B47: SME | C47: =VLOOKUP($B47,$B$2:$C$35,COLUMN(B47),FALSE) -> Senior Mechanical Engineer | D47: =SUM(E47:CH47) -> 774 | O47: 22.5 | P47: 22.5 | Q47: 18 | R47: 18 | S47: 18 | T47: 27 | U47: 27 | V47: 27 | W47: 27 | X47: 27 | Y47: 27 | Z47: 27 | AA47: 27 | AB47: 27 | AC47: 27 | AD47: 27 | AE47: 9 | AF47: 9 | AG47: 27 | AH47: 27 | AI47: 27 | AJ47: 27 | AK47: 27 | AL47: 27 | AM47: 45 | AN47: 27 | AO47: 27 | AP47: 27 | AQ47: 27 | AR47: 45
A48: 8 | B48: JPE | C48: =VLOOKUP($B48,$B$2:$C$35,COLUMN(B48),FALSE) -> PHE Engineer | D48: =SUM(E48:CH48) -> 1314 | O48: 22.5 | P48: 22.5 | Q48: 18 | R48: 18 | S48: 18 | T48: 45 | U48: 45 | V48: 45 | W48: 45 | X48: 45 | Y48: 45 | Z48: 45 | AA48: 45 | AB48: 45 | AC48: 45 | AD48: 45 | AG48: 60 | AH48: 60 | AI48: 60 | AJ48: 60 | AK48: 60 | AL48: 60 | AM48: 60 | AN48: 60 | AO48: 60 | AP48: 60 | AQ48: 60 | AR48: 60
A49: 9 | B49: JEE | C49: =VLOOKUP($B49,$B$2:$C$35,COLUMN(B49),FALSE) -> Electrical Engineer | D49: =SUM(E49:CH49) -> 1314 | O49: 22.5 | P49: 22.5 | Q49: 18 | R49: 18 | S49: 18 | T49: 45 | U49: 45 | V49: 45 | W49: 45 | X49: 45 | Y49: 45 | Z49: 45 | AA49: 45 | AB49: 45 | AC49: 45 | AD49: 45 | AG49: 60 | AH49: 60 | AI49: 60 | AJ49: 60 | AK49: 60 | AL49: 60 | AM49: 60 | AN49: 60 | AO49: 60 | AP49: 60 | AQ49: 60 | AR49: 60
A50: 10 | B50: JME | C50: =VLOOKUP($B50,$B$2:$C$35,COLUMN(B50),FALSE) -> Mechanical Engineer | D50: =SUM(E50:CH50) -> 1314 | O50: 22.5 | P50: 22.5 | Q50: 18 | R50: 18 | S50: 18 | T50: 45 | U50: 45 | V50: 45 | W50: 45 | X50: 45 | Y50: 45 | Z50: 45 | AA50: 45 | AB50: 45 | AC50: 45 | AD50: 45 | AG50: 60 | AH50: 60 | AI50: 60 | AJ50: 60 | AK50: 60 | AL50: 60 | AM50: 60 | AN50: 60 | AO50: 60 | AP50: 60 | AQ50: 60 | AR50: 60
A51: 11 | B51: BL | C51: =VLOOKUP($B51,$B$2:$C$35,COLUMN(B51),FALSE) -> BIM Manager | D51: =SUM(E51:CH51) -> 459 | O51: 9 | P51: 9 | Q51: 9 | R51: 9 | S51: 9 | T51: 18 | U51: 18 | V51: 18 | W51: 18 | X51: 18 | Y51: 18 | Z51: 18 | AA51: 18 | AB51: 18 | AC51: 18 | AD51: 18 | AG51: 18 | AH51: 18 | AI51: 18 | AJ51: 18 | AK51: 18 | AL51: 18 | AM51: 18 | AN51: 18 | AO51: 18 | AP51: 18 | AQ51: 18 | AR51: 18
A52: 12 | B52: BEL | C52: =VLOOKUP($B52,$B$2:$C$35,COLUMN(B52),FALSE) -> BIM Lead-E | D52: =SUM(E52:CH52) -> 675 | O52: 18 | P52: 9 | Q52: 9 | R52: 9 | S52: 9 | T52: 27 | U52: 27 | V52: 27 | W52: 27 | X52: 27 | Y52: 27 | Z52: 27 | AA52: 27 | AB52: 27 | AC52: 27 | AD52: 27 | AG52: 27 | AH52: 27 | AI52: 27 | AJ52: 27 | AK52: 27 | AL52: 27 | AM52: 27 | AN52: 27 | AO52: 27 | AP52: 27 | AQ52: 27 | AR52: 27
A53: 13 | B53: BML | C53: =VLOOKUP($B53,$B$2:$C$35,COLUMN(B53),FALSE) -> BIM Lead-M | D53: =SUM(E53:CH53) -> 675 | O53: 18 | P53: 9 | Q53: 9 | R53: 9 | S53: 9 | T53: 27 | U53: 27 | V53: 27 | W53: 27 | X53: 27 | Y53: 27 | Z53: 27 | AA53: 27 | AB53: 27 | AC53: 27 | AD53: 27 | AG53: 27 | AH53: 27 | AI53: 27 | AJ53: 27 | AK53: 27 | AL53: 27 | AM53: 27 | AN53: 27 | AO53: 27 | AP53: 27 | AQ53: 27 | AR53: 27
A54: 14 | B54: BPL | C54: =VLOOKUP($B54,$B$2:$C$35,COLUMN(B54),FALSE) -> BIM Lead-P | D54: =SUM(E54:CH54) -> 675 | O54: 18 | P54: 9 | Q54: 9 | R54: 9 | S54: 9 | T54: 27 | U54: 27 | V54: 27 | W54: 27 | X54: 27 | Y54: 27 | Z54: 27 | AA54: 27 | AB54: 27 | AC54: 27 | AD54: 27 | AG54: 27 | AH54: 27 | AI54: 27 | AJ54: 27 | AK54: 27 | AL54: 27 | AM54: 27 | AN54: 27 | AO54: 27 | AP54: 27 | AQ54: 27 | AR54: 27
A55: 15 | B55: BE | C55: =VLOOKUP($B55,$B$2:$C$35,COLUMN(B55),FALSE) -> BIM Modeller-E | D55: =SUM(E55:CH55) -> 1116 | O55: 45 | P55: 27 | Q55: 27 | R55: 27 | S55: 45 | U55: 45 | V55: 45 | W55: 45 | X55: 45 | Y55: 45 | Z55: 45 | AA55: 45 | AB55: 45 | AC55: 45 | AD55: 45 | AH55: 45 | AI55: 45 | AJ55: 45 | AK55: 45 | AL55: 45 | AM55: 45 | AN55: 45 | AO55: 45 | AP55: 45 | AQ55: 45 | AR55: 45
A56: 16 | B56: BE | C56: =VLOOKUP($B56,$B$2:$C$35,COLUMN(B56),FALSE) -> BIM Modeller-E | D56: =SUM(E56:CH56) -> 990 | O56: 45 | U56: 45 | V56: 45 | W56: 45 | X56: 45 | Y56: 45 | Z56: 45 | AA56: 45 | AB56: 45 | AC56: 45 | AD56: 45 | AH56: 45 | AI56: 45 | AJ56: 45 | AK56: 45 | AL56: 45 | AM56: 45 | AN56: 45 | AO56: 45 | AP56: 45 | AQ56: 45 | AR56: 45
A57: 17 | B57: BE | C57: =VLOOKUP($B57,$B$2:$C$35,COLUMN(B57),FALSE) -> BIM Modeller-E | D57: =SUM(E57:CH57) -> 945 | U57: 45 | V57: 45 | W57: 45 | X57: 45 | Y57: 45 | Z57: 45 | AA57: 45 | AB57: 45 | AC57: 45 | AD57: 45 | AH57: 45 | AI57: 45 | AJ57: 45 | AK57: 45 | AL57: 45 | AM57: 45 | AN57: 45 | AO57: 45 | AP57: 45 | AQ57: 45 | AR57: 45
A58: 18 | B58: BJE | C58: =VLOOKUP($B58,$B$2:$C$35,COLUMN(B58),FALSE) -> Junior BIM Modeller-E | D58: =SUM(E58:CH58) -> 945 | U58: 45 | V58: 45 | W58: 45 | X58: 45 | Y58: 45 | Z58: 45 | AA58: 45 | AB58: 45 | AC58: 45 | AD58: 45 | AH58: 45 | AI58: 45 | AJ58: 45 | AK58: 45 | AL58: 45 | AM58: 45 | AN58: 45 | AO58: 45 | AP58: 45 | AQ58: 45 | AR58: 45
A59: 19 | B59: BP | C59: =VLOOKUP($B59,$B$2:$C$35,COLUMN(B59),FALSE) -> BIM Modeller-P | D59: =SUM(E59:CH59) -> 1116 | O59: 45 | P59: 27 | Q59: 27 | R59: 27 | S59: 45 | U59: 45 | V59: 45 | W59: 45 | X59: 45 | Y59: 45 | Z59: 45 | AA59: 45 | AB59: 45 | AC59: 45 | AD59: 45 | AH59: 45 | AI59: 45 | AJ59: 45 | AK59: 45 | AL59: 45 | AM59: 45 | AN59: 45 | AO59: 45 | AP59: 45 | AQ59: 45 | AR59: 45
A60: 20 | B60: BP | C60: =VLOOKUP($B60,$B$2:$C$35,COLUMN(B60),FALSE) -> BIM Modeller-P | D60: =SUM(E60:CH60) -> 990 | O60: 45 | U60: 45 | V60: 45 | W60: 45 | X60: 45 | Y60: 45 | Z60: 45 | AA60: 45 | AB60: 45 | AC60: 45 | AD60: 45 | AH60: 45 | AI60: 45 | AJ60: 45 | AK60: 45 | AL60: 45 | AM60: 45 | AN60: 45 | AO60: 45 | AP60: 45 | AQ60: 45 | AR60: 45
A61: 21 | B61: BP | C61: =VLOOKUP($B61,$B$2:$C$35,COLUMN(B61),FALSE) -> BIM Modeller-P | D61: =SUM(E61:CH61) -> 945 | U61: 45 | V61: 45 | W61: 45 | X61: 45 | Y61: 45 | Z61: 45 | AA61: 45 | AB61: 45 | AC61: 45 | AD61: 45 | AH61: 45 | AI61: 45 | AJ61: 45 | AK61: 45 | AL61: 45 | AM61: 45 | AN61: 45 | AO61: 45 | AP61: 45 | AQ61: 45 | AR61: 45
A62: 22 | B62: BJP | C62: =VLOOKUP($B62,$B$2:$C$35,COLUMN(B62),FALSE) -> Junior BIM Modeller-P | D62: =SUM(E62:CH62) -> 945 | U62: 45 | V62: 45 | W62: 45 | X62: 45 | Y62: 45 | Z62: 45 | AA62: 45 | AB62: 45 | AC62: 45 | AD62: 45 | AH62: 45 | AI62: 45 | AJ62: 45 | AK62: 45 | AL62: 45 | AM62: 45 | AN62: 45 | AO62: 45 | AP62: 45 | AQ62: 45 | AR62: 45
A63: 23 | B63: BM | C63: =VLOOKUP($B63,$B$2:$C$35,COLUMN(B63),FALSE) -> BIM Modeller-M | D63: =SUM(E63:CH63) -> 1116 | O63: 45 | P63: 27 | Q63: 27 | R63: 27 | S63: 45 | U63: 45 | V63: 45 | W63: 45 | X63: 45 | Y63: 45 | Z63: 45 | AA63: 45 | AB63: 45 | AC63: 45 | AD63: 45 | AH63: 45 | AI63: 45 | AJ63: 45 | AK63: 45 | AL63: 45 | AM63: 45 | AN63: 45 | AO63: 45 | AP63: 45 | AQ63: 45 | AR63: 45
A64: 24 | B64: BM | C64: =VLOOKUP($B64,$B$2:$C$35,COLUMN(B64),FALSE) -> BIM Modeller-M | D64: =SUM(E64:CH64) -> 1035 | O64: 45 | S64: 45 | U64: 45 | V64: 45 | W64: 45 | X64: 45 | Y64: 45 | Z64: 45 | AA64: 45 | AB64: 45 | AC64: 45 | AD64: 45 | AH64: 45 | AI64: 45 | AJ64: 45 | AK64: 45 | AL64: 45 | AM64: 45 | AN64: 45 | AO64: 45 | AP64: 45 | AQ64: 45 | AR64: 45
A65: 25 | B65: BM | C65: =VLOOKUP($B65,$B$2:$C$35,COLUMN(B65),FALSE) -> BIM Modeller-M | D65: =SUM(E65:CH65) -> 990 | O65: 45 | U65: 45 | V65: 45 | W65: 45 | X65: 45 | Y65: 45 | Z65: 45 | AA65: 45 | AB65: 45 | AC65: 45 | AD65: 45 | AH65: 45 | AI65: 45 | AJ65: 45 | AK65: 45 | AL65: 45 | AM65: 45 | AN65: 45 | AO65: 45 | AP65: 45 | AQ65: 45 | AR65: 45
A66: 26 | B66: BJM | C66: =VLOOKUP($B66,$B$2:$C$35,COLUMN(B66),FALSE) -> Junior BIM Modeller-M | D66: =SUM(E66:CH66) -> 945 | U66: 45 | V66: 45 | W66: 45 | X66: 45 | Y66: 45 | Z66: 45 | AA66: 45 | AB66: 45 | AC66: 45 | AD66: 45 | AH66: 45 | AI66: 45 | AJ66: 45 | AK66: 45 | AL66: 45 | AM66: 45 | AN66: 45 | AO66: 45 | AP66: 45 | AQ66: 45 | AR66: 45
C67: Total Full Time Equivalent (FTE) | E67: =SUM(E39:E66)/45 -> 0 | F67: =SUM(F39:F66)/45 -> 0 | G67: =SUM(G39:G66)/45 -> 0 | H67: =SUM(H39:H66)/45 -> 0 | I67: =SUM(I39:I66)/45 -> 0 | J67: =SUM(J39:J66)/45 -> 0 | K67: =SUM(K39:K66)/45 -> 0 | L67: =SUM(L39:L66)/45 -> 0 | ... AX67: =SUM(AX39:AX66)/45 -> 0

Sheet Tender List
A2: MIRAGE LEISURE AND DEVELOPMENT
A4: DUBAI CREEK HARBOUR PLOT A9 & A10, RESIDENTIAL TOWERS
A6: MIRAGE SCOPE OF SERVICES: LEAD DESIGN CONSULTANCY
A8: SUB-CONSULTANT TENDER LIST
A10: ITEM | B10: SCOPE & TENDERER | C10: CONTACT PERSON | D10: EMAIL ADDRESS
A12: 2 | B12: Architecture (Pre-Concept Architect) - N/A
A14: =A12+1 -> 3 | B14: AOR - N/A
A15: =#REF!+0.01 -> #REF! | C15: Gopan Raj | D15: g.raj@wmeglobal.com
A18: =+A14+1 -> 4 | B18: Geotechnical Design - N/A
A20: =+A18+1 -> 5 | B20: MEP
A21: =A20+0.01 -> 5.01 | B21: Green Concept Engineering Consulatnt (GCE) | C21: Amjad Nassar Bassam | D21: amjad@greencec.ae bassam@greencec.ae
A22: =A21+0.01 -> 5.02 | B22: CKR Consulting Engineers | C22: Anil Menon | D22: amenon@ckr.ae
A23: =A22+0.01 -> 5.03 | B23: NV5 | C23: Nathan Cartwright | D23: nathan.cartwright@nv5.com
A25: =+A20+1 -> 6 | B25: Interior Design
A26: =A25+0.01 -> 6.01 | B26: PH Design | C26: Robert Hawkins Pinar Hawkins | D26: admin@phdesignme.com pinarh@phdesignme.com
A27: =A26+0.01 -> 6.02 | B27: LW Design | C27: Emily Webb | D27: emily.webb@lw.co
A28: =A27+0.01 -> 6.03 | B28: DSGN | C28: Trevor Julius | D28: Trevor@dsgn.co.za
A29: =#REF!+0.01 -> #REF!
A30: =A29+0.01 -> #REF!
A32: =+A25+1 -> 7 | B32: Specialist Lighting
A33: =A32+0.01 -> 7.01 | B33: Studio Lumen | C33: Siddharth Mathur | D33: sm@studiolumen.ae rv@studiolumen.ae sr@studiolumen.ae vp@studiolumen.ae
A34: =A33+0.01 -> 7.02 | B34: Lightvision | C34: Karsten Ehling | D34: karsten.ehling@lichtvision.com
A35: =A34+0.01 -> 7.03 | B35: CD+M Lighting (Dubai) | C35: Asera Banu | D35: Asera@cdmlight.com
A36: =A35+0.01 -> 7.04 | B36: Nulty Lighting | C36: Mark Vowles | D36: mark@nultylighting.co.uk
A37: =A36+0.01 -> 7.05 | B37: LDPi | C37: Lawrie Nisbet | D37: lnisbet@ldpinternational.com
A39: =A32+1 -> 8 | B39: Façade and BMU
A40: =A39+0.01 -> 8.01 | B40: MeinHardt | C40: Paul Grove Celeste Gariando Mary Rose Joyce Gaa | D40: paul.grove@mfacade.com celeste.gariando@mfacade.com joyce.gaa@mfacade.com
A41: =A40+0.01 -> 8.02 | B41: Thomas Bell-Wright | C41: Mutaz Saheb | D41: mutaz.saheb@bell-wright.com
A42: =A41+0.01 -> 8.03 | B42: AESG | C42: Scott Coombes | D42: s.coombes@aesg-me.com
A43: =A42+0.01 -> 8.04 | B43: Ramboll | C43: Afschin Soleimani | D43: a.soleimani@ramboll.com
A44: =A43+0.01 -> 8.05 | B44: Werner Sobek | C44: Benjamin Beer Remoleza Bagaporo | D44: benjamin.beer@wernersobek.com bids.dubai@wernersobek.com
A46: =+A39+1 -> 9 | B46: Signage & Wayfinding
A47: =A46+0.01 -> 9.01 | B47: Trade Inc | C47: Ghouthia Johnson Chris McCreedy | D47: Ghouthia@tradeinc.ae chrism@tradeinc.ae
A48: =A47+0.01 -> 9.02 | B48: Brimaxx | C48: Christian Berglehner Carlo Schwarzler | D48: chris@brimaxx.eu chris@brimaxx-limo.com carlo@brimaxx.eu
A49: =A48+0.01 -> 9.03 | B49: Endpoint | C49: Nicole Sassaman | D49: nicole.sassaman@weareendpoint.com
A51: =+A46+1 -> 10 | B51: Wind Tunnel Testing
A52: =A51+0.01 -> 10.01 | B52: CPP | C52: Bhami Ilyas Dr. Roy Denoon | D52: bilyas@cppwind.com rdenoon@cppwind.com
A53: =A52+0.01 -> 10.02 | B53: RWDI | C53: Chrissy Lemmex | D53: Christine.Lemmex@RWDI.com
A55: =+A51+1 -> 11 | B55: Security (including Threat & Risk Assessment )
A56: =A55+0.01 -> 11.01 | B56: CKR Consulting Engineers | C56: Anil Menon | D56: amenon@ckr.ae
A57: =A56+0.01 -> 11.02 | B57: Jensen Hughes | C57: Pedro Armijo | D57: tenders@jensenhughes.com
A59: =A55+1 -> 12 | B59: Telecom (AV/CT)
A60: =A59+0.01 -> 12.01 | B60: Emaar Technologies | C60: Ganesh Mitkari Mohammed Shakeel Neranki | D60: ganeshm@emaar.ae MShakeel@emaar.ae
A62: =A59+1 -> 13 | B62: Landscape - N/A
A64: =A62+1 -> 14 | B64: Pool and Water Specialist
A65: =A64+0.01 -> 14.01 | B65: Barr + Wray | C65: Peter Rietveld | D65: prietveld@barrandwray.com
A66: =A65+0.01 -> 14.02 | B66: Starpool | C66: Gabriele Marezzi | D66: gabriele.marezzi@starpool.com
A67: =A66+0.01 -> 14.03 | B67: EME - Engineering Marketing EST | C67: Nayef Kassissieh | D67: nayef@eme-me.com
A68: =A67+0.01 -> 14.04 | B68: The Wellness | C68: Noha Khalil | D68: noha.khalil@thewellness.ae
A70: =A64+1 -> 15 | B70: Fire Life Safety
A71: =A70+0.01 -> 15.01 | B71: Vortex Fire Safety Consultancy | C71: Faimeen Shah Katherine Brownlie | D71: f.shah@vortexfec.com k.brownlie@vortexfec.com a.joy@vortexfec.com dubai@vortexfec.com
A72: =A71+0.01 -> 15.02 | B72: Design Confidence | C72: Tom Sagris | D72: tsagris@designconfidence.com
A73: =A72+0.01 -> 15.03 | B73: Jensen Hughes | C73: Pedro Armijo | D73: tenders@jensenhughes.com
A75: =A70+1 -> 16 | B75: Vertical Transport
A76: =A75+0.01 -> 16.01 | B76: Barker Mohandas | C76: Anand Sivan Sivakumar Rangaraj | D76: as@barkermohandas.com
A77: =A76+0.01 -> 16.02 | B77: RBA | C77: Anthony Lewis | D77: anthony@rbavt.com
A79: =A75+1 -> 17 | B79: Traffic Impact Study
A80: =A79+0.01 -> 17.01 | B80: Al Turat Engineering Consultants | C80: Tammam Rashid Majid Semsar Mohaned Alaa Mukdad Rawaa Najjar | D80: tammam@tec.ae rashed@TEC.AE majid@tec.ae mohdm@tec.ae alaa@tecdxb.com Rawaa@tec.ae
A81: =A80+0.01 -> 17.02 | B81: Zutari | C81: Sean Murphy | D81: Sean.Murphy2@zutari.com
A82: =A81+0.01 -> 17.03 | B82: Infracad | C82: Hani Al-Alami | D82: Hani.al-alami@infracad.com khaled.Nahouli@infracad.com
A84: =A79+1 -> 18 | B84: Acoustics
A85: =A84+0.01 -> 18.01 | B85: Inhabit Group | C85: Gerald Stewart | D85: Gerald.Stewart@inhabitgroup.com
A86: =A85+0.01 -> 18.02 | B86: Ramboll | C86: Afschin Soleimani | D86: a.soleimani@ramboll.com
A87: =A86+0.01 -> 18.03 | B87: DARL | C87: 0 | D87: admin@darl.ae nadia@darl.ae tijana@darl.ae
A89: =A84+1 -> 19 | B89: 3rd Party Structural Review
A90: =A89+0.01 -> 19.01 | B90: SSE | C90: Marianne Magdy | D90: mmagdy@sseweb.ae
A91: =A90+0.01 -> 19.02 | B91: Qualiconsult | C91: Khaleed Ben Hamouda | D91: khaled.ben-hamouda@qualiconsult-uae.com
A93: =A89+1 -> 20 | B93: 3rd Party Geotechnical Review
A94: =A93+0.01 -> 20.01 | B94: SSE | C94: Marianne Magdy | D94: mmagdy@sseweb.ae
A95: =A94+0.01 -> 20.02 | B95: Qualiconsult | C95: Khaleed Ben Hamouda | D95: khaled.ben-hamouda@qualiconsult-uae.com
A97: =A93+1 -> 21 | B97: Aeronautical
A98: =A97+0.01 -> 21.01 | B98: Nortech Infra | C98: Avinash Paul Dsouza | D98: paul.dsouza@nortechservices.net
A100: =A97+1 -> 22 | B100: DMGBC / Al Sa’fat Green Building Facilitation
A101: =A100+0.01 -> 22.01 | B101: PSDI | C101: Ramesh Narayanan | D101: ramesh@platinumsdi.com
A103: =A100+1 -> 23 | B103: Waste Management Consultancy
A104: =A103+0.01 -> 23.01 | B104: CDS Consulting and Design Services | C104: Karim Nasreddine | D104: karim.n@cdsmea.com>
A105: =A104+0.01 -> 23.02 | B105: MCTS | C105: Ana Maria Velez | D105: ana@mctservices.com
A108: APPROVAL
A109: 1 | B109: Commercial Lead | C109: Raihan Saghir | D109: 45443
A110: 2 | B110: Executive Director | C110: N/A
A111: 3 | B111: Managing Director | C111: Andre Naude | D111: 44470
A112: 3 | B112: Chief Executive Officer | C112: Amar Tahilani | D112: 45443
